{
    "pixelData": [{"data": "gay5v8W2w8oIDzl/qogvWdLVtMIjIyMjIyMjI096/w=="},
{"skip":496},
{"data": "//////8="},
{"skip":28},
{"data": "/////w=="},
{"skip":27},
{"data": "/////w=="},
{"skip":60},
{"data": "/////w=="},
{"skip":29},
{"data": "/////w=="},
{"skip":27},
{"data": "////"},
{"skip":59},
{"data": "//////8="},
{"skip":124},
{"data": "/////w=="},
{"skip":27},
{"data": "/////w=="},
{"skip":30},
{"data": "////"},
{"skip":60},
{"data": "/6yBgYGs//8="},
{"skip":24},
{"data": "//+sgYGB//8="},
{"skip":23},
{"data": "//+sgYGs/w=="},
{"skip":27},
{"data": "//////8="},
{"skip":26},
{"data": "/6yBgYH//w=="},
{"skip":25},
{"data": "//+sgYGB/w=="},
{"skip":24},
{"data": "//+sgYH/"},
{"skip":28},
{"data": "/////w=="},
{"skip":25},
{"data": "/6yBgYGs/w=="},
{"skip":26},
{"data": "//////8="},
{"skip":27},
{"data": "//////8="},
{"skip":27},
{"data": "//////8="},
{"skip":26},
{"data": "//+BgYGs/w=="},
{"skip":25},
{"data": "/4GBgaz//w=="},
{"skip":27},
{"data": "/4GBrP//"},
{"skip":26},
{"data": "/////w=="},
{"skip":28},
{"data": "/4GBgays/w=="},
{"skip":24},
{"data": "/6yBgYGsrKz/"},
{"skip":22},
{"data": "/6yBgYGsrP8="},
{"skip":26},
{"data": "/6yBgYGs/w=="},
{"skip":25},
{"data": "/4GBrKys/w=="},
{"skip":24},
{"data": "/6yBgYGsrP8="},
{"skip":23},
{"data": "/6yBgYGsrP8="},
{"skip":26},
{"data": "/6yBgYH//w=="},
{"skip":23},
{"data": "/4Gsgf+B/w=="},
{"skip":25},
{"data": "/6yBgYGs/w=="},
{"skip":25},
{"data": "/6yBgYGs/w=="},
{"skip":25},
{"data": "/6yBgYGs/w=="},
{"skip":25},
{"data": "/6ysrIGB/w=="},
{"skip":25},
{"data": "/6ysgYGBrP8="},
{"skip":25},
{"data": "/6ysgYGBrP8="},
{"skip":23},
{"data": "//+BgYGs/w=="},
{"skip":26},
{"data": "/6yB/6z//w=="},
{"skip":25},
{"data": "/4GB/6z//6z/"},
{"skip":23},
{"data": "/4Gs/6z//w=="},
{"skip":26},
{"data": "/4GBgays/w=="},
{"skip":24},
{"data": "/4H/gf///w=="},
{"skip":25},
{"data": "/4H/gf///w=="},
{"skip":25},
{"data": "/4H/gf///w=="},
{"skip":26},
{"data": "/4GBrKys/w=="},
{"skip":22},
{"data": "/6ysgf8P/6z/"},
{"skip":23},
{"data": "/4GBrIH/gf8="},
{"skip":25},
{"data": "/4Gsgf+Bgf8="},
{"skip":24},
{"data": "/4Gsgf+B/w=="},
{"skip":26},
{"data": "////gf+B/w=="},
{"skip":25},
{"data": "////gf+B/w=="},
{"skip":25},
{"data": "////gf+s/w=="},
{"skip":24},
{"data": "/6ysrIGBgf//"},
{"skip":24},
{"data": "/4H/D/85/w=="},
{"skip":25},
{"data": "/4H/D/85//8="},
{"skip":23},
{"data": "/4Gs/w//Of8="},
{"skip":25},
{"data": "/6yB/6z//w=="},
{"skip":25},
{"data": "//8P/zk5//8="},
{"skip":24},
{"data": "//8P/zk5/w=="},
{"skip":24},
{"data": "/6z/D/85Of8="},
{"skip":25},
{"data": "/4H/gf///w=="},
{"skip":23},
{"data": "/4H//wg5/4H/"},
{"skip":22},
{"data": "/6yBrIH/D/+s/w=="},
{"skip":24},
{"data": "/6yB/w//gaz/"},
{"skip":22},
{"data": "/6ysgf8P/6z/"},
{"skip":24},
{"data": "//85Of8P//8="},
{"skip":25},
{"data": "/zk5/w///w=="},
{"skip":25},
{"data": "/zk5/w//rP8="},
{"skip":24},
{"data": "////gf+B/zn/"},
{"skip":22},
{"data": "/6yB//8ICP8="},
{"skip":25},
{"data": "/6z/OQgI/w=="},
{"skip":25},
{"data": "/6z/OQgI/w=="},
{"skip":25},
{"data": "/4H/D/85/w=="},
{"skip":9},
{"data": "////"},
{"skip":13},
{"data": "/6z/DwgI/7b/"},
{"skip":23},
{"data": "/6z/DwgI////"},
{"skip":22},
{"data": "/4Gs/w8ICP8="},
{"skip":26},
{"data": "/w//OTn/"},
{"skip":23},
{"data": "/4H/DwgP/4H/"},
{"skip":22},
{"data": "/4Gs//8IOf+B//8="},
{"skip":21},
{"data": "//+s//8IOf+sgf8="},
{"skip":20},
{"data": "////gf//CDn///8="},
{"skip":23},
{"data": "/7b/CAgP/6z/"},
{"skip":23},
{"data": "////CAgP/6z/"},
{"skip":25},
{"data": "/wgID/+sgf8="},
{"skip":24},
{"data": "/zk5/w//////"},
{"skip":22},
{"data": "////D/8POf8="},
{"skip":25},
{"data": "//+s/w85//8="},
{"skip":24},
{"data": "//8P/w85/w=="},
{"skip":24},
{"data": "/////zkICP////8="},
{"skip":4},
{"data": "//8ID/8="},
{"skip":13},
{"data": "//8P/w85/7b/"},
{"skip":22},
{"data": "//////8POf+2tv8="},
{"skip":22},
{"data": "//8P/w85//8="},
{"skip":23},
{"data": "/////w8ICP8="},
{"skip":21},
{"data": "////rP85Dzn/rP///w=="},
{"skip":21},
{"data": "/6z/DwgP//+2tv8="},
{"skip":19},
{"data": "/7a2//8PCA//rP8="},
{"skip":20},
{"data": "/wgP/6z/DwgP/w=="},
{"skip":25},
{"data": "/7b/OQ//D///"},
{"skip":22},
{"data": "/7a2/zkP/w////8="},
{"skip":23},
{"data": "//85D/8P//8="},
{"skip":25},
{"data": "/wgID/+BrP/D/w=="},
{"skip":21},
{"data": "/1kv/zn/D/8="},
{"skip":24},
{"data": "/y/D/zn/D///"},
{"skip":23},
{"data": "/7a2////D/8="},
{"skip":23},
{"data": "/7a2/zn/Dzn/w7a2/////7b/Dzn/"},
{"skip":12},
{"data": "/1n//zn/D//K/w=="},
{"skip":21},
{"data": "/1kvw/85/w//trb/"},
{"skip":22},
{"data": "////Of8P//8="},
{"skip":22},
{"data": "//8ID///Dzn/"},
{"skip":20},
{"data": "/7a2Wf///wj///+2trb/"},
{"skip":19},
{"data": "/////zkPOf+2trbD//8="},
{"skip":15},
{"data": "///DtsMv/zkPOf//gf8="},
{"skip":19},
{"data": "/w85////OQ85/w=="},
{"skip":25},
{"data": "/8r/D/85//+2/w=="},
{"skip":21},
{"data": "/7a2/w//Of+2trb/"},
{"skip":22},
{"data": "//8P/zn///8="},
{"skip":25},
{"data": "/zn//6yB/8r/w/8="},
{"skip":20},
{"data": "/7ZZL/85/w=="},
{"skip":24},
{"data": "/7ZZL8P/Of///w=="},
{"skip":22},
{"data": "/8O2wy9ZWf8="},
{"skip":24},
{"data": "/8r//////w//w8PDysO2trb///8="},
{"skip":12},
{"data": "/7ZZL8P/Of/D//8="},
{"skip":21},
{"data": "/7ZZL8P/Of/DysP/"},
{"skip":21},
{"data": "/1kvL/85/8r/"},
{"skip":21},
{"data": "////Dzn/Of8P//8="},
{"skip":19},
{"data": "/8O2WS//Of85/7a2tsP/"},
{"skip":18},
{"data": "/y8vw///CP//tsPDw8PK/w=="},
{"skip":13},
{"data": "/8rDw8PDL///CP//tv+2/w=="},
{"skip":17},
{"data": "/8P///8v//8I////"},
{"skip":24},
{"data": "//9Z/zn/tra2tv8="},
{"skip":20},
{"data": "/8PKL/85/7a2trb/"},
{"skip":22},
{"data": "/8r/Of+2trb/"},
{"skip":24},
{"data": "//+2/4Gs/8r/yv8="},
{"skip":20},
{"data": "/7a2WS//w/8="},
{"skip":23},
{"data": "/7a2WS/D/8P/w/8="},
{"skip":21},
{"data": "///DL1m2tv8="},
{"skip":23},
{"data": "/7b/tv8PCP//w8r/////////"},
{"skip":15},
{"data": "/8O2WS/D/8PD//8="},
{"skip":20},
{"data": "/8rDtlkvw//Dw//D/w=="},
{"skip":21},
{"data": "/7ZZWS//w8r/"},
{"skip":20},
{"data": "/7a2w/////+2/7a2/w=="},
{"skip":18},
{"data": "/8PDylkv/w//w8PDw8P/"},
{"skip":17},
{"data": "/7bKWS8v////w8PDysrDw8P/"},
{"skip":11},
{"data": "/8PDw8rKwy/D////w7a2trb/"},
{"skip":16},
{"data": "/8PKyv8v/zn//7bD/w=="},
{"skip":23},
{"data": "//9ZL//Dw7a2w/8="},
{"skip":20},
{"data": "/8P/L8P/w8PDw8PK/w=="},
{"skip":21},
{"data": "/8ov/8O2trb/"},
{"skip":23},
{"data": "/7a2trb//1n///8="},
{"skip":21},
{"data": "/8PDylkvw/8="},
{"skip":23},
{"data": "/8PDw1kvw8P/w/8="},
{"skip":21},
{"data": "///DL8rDw/8="},
{"skip":22},
{"data": "/8P/tsP/OTn/w8P/"},
{"skip":22},
{"data": "/8PDylkvw8PD//8="},
{"skip":20},
{"data": "/8PDw8pZL8PDw//D/w=="},
{"skip":21},
{"data": "/8PKylkvL8r/"},
{"skip":20},
{"data": "/8PD/8pZ/8PDw7a2tv//"},
{"skip":16},
{"data": "/8P/w8pZL//Dw8PK/8P/"},
{"skip":17},
{"data": "/8O2yspZL//Dw8PK////w8P/"},
{"skip":11},
{"data": "/8PD////ylkvw//Dw8O2tsP/"},
{"skip":16},
{"data": "/8rK//9ZL///tra2/w=="},
{"skip":23},
{"data": "///KL8PDw8PDw/8="},
{"skip":20},
{"data": "/8P/WS/Dw8PDysPD/w=="},
{"skip":21},
{"data": "/8ovw8PDw8P/"},
{"skip":21},
{"data": "///Dw7a2w8Mvyv8="},
{"skip":23},
{"data": "/8PD/8pZL/8="},
{"skip":22},
{"data": "/8rDw//DWS/D/8P/"},
{"skip":20},
{"data": "/8P/L1nKw8P/"},
{"skip":22},
{"data": "///Dw//////Dw8r/"},
{"skip":21},
{"data": "/8rDysrKWS/Dw//D/w=="},
{"skip":19},
{"data": "/8PD/8PKWS/Dw//D/w=="},
{"skip":20},
{"data": "/8PDw8PKWVkv/w=="},
{"skip":20},
{"data": "/////8pZWcPDw8PDw8PK/w=="},
{"skip":2},
{"data": "////"},
{"skip":10},
{"data": "/8P/ysPKWS/Dw8PK/8P/"},
{"skip":17},
{"data": "/8PDw8rKWS8vw8P/"},
{"skip":2},
{"data": "/8PK/w=="},
{"skip":11},
{"data": "/8rD/w=="},
{"skip":2},
{"data": "/8ovw8PDw8PDw8P/"},
{"skip":17},
{"data": "//8="},
{"skip":1},
{"data": "/8ov/8PDtsr/"},
{"skip":22},
{"data": "/8P/ylkvw8PDysPK/w=="},
{"skip":18},
{"data": "/8PD/8ovw8PDw//Dw/8="},
{"skip":21},
{"data": "/8ovw8PDw8PD/w=="},
{"skip":17},
{"data": "////ysPDw8PDw8Mvyv8="},
{"skip":23},
{"data": "/8PD/8rKL/8="},
{"skip":22},
{"data": "/8PD/8rDwy/D/8O2/w=="},
{"skip":19},
{"data": "/8P/L8rKw8PD/w=="},
{"skip":21},
{"data": "/8rK///Kylkvw/8="},
{"skip":22},
{"data": "/8PDysrDylkvw//D/w=="},
{"skip":18},
{"data": "/8rD///Kw8pZL8r/w8P/"},
{"skip":19},
{"data": "/8PDysPDyspZ/w=="},
{"skip":24},
{"data": "/8ovw8PDyv/Kw7a2//8PCP8="},
{"skip":10},
{"data": "/8PK/8PDylkvw8P/ysP/"},
{"skip":17},
{"data": "/8PDw//DyspZL8P/"},
{"skip":2},
{"data": "/8P//w=="},
{"skip":12},
{"data": "/8P/"},
{"skip":2},
{"data": "/8pZL8PDw//Dw8P/"},
{"skip":20},
{"data": "/8ov/8PD/7a2/w=="},
{"skip":21},
{"data": "/8P/w8ovw8PKysPD/w=="},
{"skip":18},
{"data": "/8O2/8pZL8PDyv//w8r/"},
{"skip":20},
{"data": "/8pZL8PDysPD/w=="},
{"skip":14},
{"data": "////tra2tsPK/8rDw8Mvyv8="},
{"skip":23},
{"data": "/8PD/8rDWf8="},
{"skip":22},
{"data": "/8PD/8rDw1kv/8q2/w=="},
{"skip":19},
{"data": "/8P/WcrK/8PD/w=="},
{"skip":21},
{"data": "////"},
{"skip":1},
{"data": "/8rDyi/K/w=="},
{"skip":22},
{"data": "/8PD/8rKw8pZL/+2/w=="},
{"skip":18},
{"data": "/8PD///KysPKWVn/w7b/"},
{"skip":19},
{"data": "/8PD/8rDysPK/w=="},
{"skip":24},
{"data": "/8ovw8PD/w=="},
{"skip":1},
{"data": "///Dtrb/CDn/"},
{"skip":10},
{"data": "/8PD/8rDw8pZL8r/w8P/"},
{"skip":17},
{"data": "/8rDw//Kw8rKWS//"},
{"skip":2},
{"data": "////"},
{"skip":13},
{"data": "////"},
{"skip":2},
{"data": "/8rKWS/Dyv/Dw8r/"},
{"skip":20},
{"data": "/8pZL8PK/8P//w=="},
{"skip":21},
{"data": "/7b/yspZL8PK/8PD/w=="},
{"skip":18},
{"data": "/7bD/8rKL8PDyv//w8P/"},
{"skip":20},
{"data": "/8rKL8PD/8PD/w=="},
{"skip":14},
{"data": "/wgP/8PDw///"},
{"skip":1},
{"data": "/8PDL1nK/w=="},
{"skip":23},
{"data": "/8PD/8PDyv8="},
{"skip":22},
{"data": "/8PD/8rDw8Mv///Dtv8="},
{"skip":17},
{"data": "/8PD/8rKyv/Dw/8="},
{"skip":25},
{"data": "/8PKw1kv/w=="},
{"skip":22},
{"data": "/8PD/8rDysPKWf+2/w=="},
{"skip":18},
{"data": "/8P/"},
{"skip":2},
{"data": "/8PKw8rK//+2/w=="},
{"skip":19},
{"data": "/8PD/8PKw8rK/w=="},
{"skip":24},
{"data": "/8pZL8PD/w=="},
{"skip":3},
{"data": "////////"},
{"skip":11},
{"data": "/8O2/8PKw8rKWS//tsP/"},
{"skip":18},
{"data": "/8PD/8PKw8rKWf8="},
{"skip":1},
{"data": "/wg5/w=="},
{"skip":13},
{"data": "/w8I/w=="},
{"skip":1},
{"data": "/8PKylkvw//Dw/8="},
{"skip":21},
{"data": "/8rKL8PKyv8ICP8="},
{"skip":20},
{"data": "/7b/ysPKL8rK/8PD/w=="},
{"skip":18},
{"data": "/7b//8rKWS/D/w=="},
{"skip":2},
{"data": "/8P/"},
{"skip":20},
{"data": "/8rKL8PD/8PD/w=="},
{"skip":14},
{"data": "/zkI/////w=="},
{"skip":3},
{"data": "/8PDL8r/"},
{"skip":24},
{"data": "/7bD/8rDw/8="},
{"skip":22},
{"data": "/8P//8rDw8pZ/w=="},
{"skip":1},
{"data": "/8P/"},
{"skip":17},
{"data": "/8P/"},
{"skip":1},
{"data": "/y8vyv+2w/8="},
{"skip":24},
{"data": "/8rDyspZ/w=="},
{"skip":22},
{"data": "/7bK///Kw8rKL/+2/w=="},
{"skip":17},
{"data": "/8PD/w=="},
{"skip":2},
{"data": "/8rDysov///Dtv8="},
{"skip":19},
{"data": "/8PD/8PKyi//"},
{"skip":24},
{"data": "/8rKL8PK/w=="},
{"skip":20},
{"data": "/7a2/8rDysPKyln/trb/"},
{"skip":18},
{"data": "/8PD/8rDysPKyv8="},
{"skip":1},
{"data": "//8P/w=="},
{"skip":13},
{"data": "/wg5/w=="},
{"skip":1},
{"data": "/8rDysrKWf/Dw/8="},
{"skip":22},
{"data": "/8pZL8rK/zkP/w=="},
{"skip":20},
{"data": "/7b/L8rKWS///8q2/w=="},
{"skip":17},
{"data": "///D//8vyspZL/8="},
{"skip":2},
{"data": "/8PD/w=="},
{"skip":19},
{"data": "/y/KWS//w8P/"},
{"skip":16},
{"data": "//8="},
{"skip":7},
{"data": "/8MvWcr/"},
{"skip":24},
{"data": "/7a2/8rKw/8="},
{"skip":21},
{"data": "/8PD//8vw8ov/w=="},
{"skip":2},
{"data": "//8I/w=="},
{"skip":16},
{"data": "////"},
{"skip":1},
{"data": "/1lZL//Dtv8="},
{"skip":24},
{"data": "/8rKysov/w=="},
{"skip":22},
{"data": "/7b////KysovWf///w=="},
{"skip":17},
{"data": "/8P/"},
{"skip":3},
{"data": "/8rKyi9Z/w=="},
{"skip":1},
{"data": "////"},
{"skip":19},
{"data": "/7bD/8rKL1n/"},
{"skip":24},
{"data": "/y/KWS//"},
{"skip":21},
{"data": "/7bD/y/KysrKyi//w7b/"},
{"skip":18},
{"data": "/8O2/y/KysrKyv8="},
{"skip":3},
{"data": "/w=="},
{"skip":15},
{"data": "//8="},
{"skip":2},
{"data": "/8rKysrKL/+2w/8="},
{"skip":22},
{"data": "/y/KWS/K////"},
{"skip":21},
{"data": "////WS/Kyln///+2/w=="},
{"skip":16},
{"data": "/wgP/w=="},
{"skip":1},
{"data": "/1kvyspZ/w=="},
{"skip":3},
{"data": "/8P/"},
{"skip":19},
{"data": "/1kvyln/w7b/"},
{"skip":25},
{"data": "/y9Zysov/w=="},
{"skip":23},
{"data": "/7a2/y8v/w//"},
{"skip":20},
{"data": "/8PD//9ZLy9Z/w=="},
{"skip":2},
{"data": "/w85/w=="},
{"skip":16},
{"data": "/wj/"},
{"skip":1},
{"data": "/8rKWVn/w7b//w=="},
{"skip":22},
{"data": "/y/Kyi9Z/w=="},
{"skip":22},
{"data": "/7b/"},
{"skip":1},
{"data": "/y8vL1nK/w//"},
{"skip":17},
{"data": "////"},
{"skip":3},
{"data": "/y8vL1nK/w=="},
{"skip":1},
{"data": "/zkI/w=="},
{"skip":19},
{"data": "/7bD/y9Zyv8="},
{"skip":24},
{"data": "/1kvyln/"},
{"skip":21},
{"data": "/7bK/1kvLy8vL1n/yrb/"},
{"skip":18},
{"data": "/7b//1kvLy8vL/8="},
{"skip":23},
{"data": "/y8vLy8vWf//tv8="},
{"skip":21},
{"data": "//9ZL8pZL/8="},
{"skip":23},
{"data": "/w//ylkvLy//"},
{"skip":1},
{"data": "/7b/"},
{"skip":16},
{"data": "/wj/"},
{"skip":2},
{"data": "/8pZLy8v/w=="},
{"skip":3},
{"data": "////"},
{"skip":19},
{"data": "/8pZL//Dtv8="},
{"skip":26},
{"data": "/1nKyi9Z/w=="},
{"skip":23},
{"data": "/8O2/1lZ/zn/"},
{"skip":20},
{"data": "////"},
{"skip":1},
{"data": "/8pZWcr/"},
{"skip":2},
{"data": "////"},
{"skip":16},
{"data": "/wgP/w=="},
{"skip":1},
{"data": "/8rDysrK/8P/CP8="},
{"skip":21},
{"data": "/1kvL1nKyv8="},
{"skip":21},
{"data": "/7b/"},
{"skip":1},
{"data": "/1lZWcrK/zn/"},
{"skip":16},
{"data": "/w8I/w=="},
{"skip":3},
{"data": "/1lZWcrK/w=="},
{"skip":1},
{"data": "/w8P/w=="},
{"skip":19},
{"data": "//+2/1nKw8r/"},
{"skip":22},
{"data": "/8PKWS8vL/8="},
{"skip":20},
{"data": "/7b//8pZWVlZWcr//7b/"},
{"skip":19},
{"data": "/w8I/1lZWVlZ/w=="},
{"skip":23},
{"data": "/1lZWVlZ/wgP/w=="},
{"skip":22},
{"data": "/8rKWS8vWf8="},
{"skip":23},
{"data": "/wj/yspZWVn/"},
{"skip":1},
{"data": "/7b/"},
{"skip":17},
{"data": "/w=="},
{"skip":3},
{"data": "/8rKWVlZ/w=="},
{"skip":3},
{"data": "/wgP/w=="},
{"skip":17},
{"data": "/8rDyln/tv//"},
{"skip":26},
{"data": "/y8vL1nK/w=="},
{"skip":23},
{"data": "/////8rKw/8="},
{"skip":21},
{"data": "/wgP/8PKysrDw/8="},
{"skip":21},
{"data": "//8="},
{"skip":2},
{"data": "/8PDysrK//85D/8="},
{"skip":21},
{"data": "/8pZWcrK//8="},
{"skip":21},
{"data": "//8="},
{"skip":1},
{"data": "/8rKysrDw///"},
{"skip":17},
{"data": "/zn/"},
{"skip":3},
{"data": "/8rKysrD/w=="},
{"skip":3},
{"data": "//8="},
{"skip":21},
{"data": "//8I/8rDw/8="},
{"skip":22},
{"data": "/8PKyllZWf8="},
{"skip":20},
{"data": "////ysPKysrKysPK////"},
{"skip":19},
{"data": "/wg5/8rKysrK/w=="},
{"skip":23},
{"data": "/8rKysrK/zkI/w=="},
{"skip":22},
{"data": "/8rKyllZWf//"},
{"skip":23},
{"data": "///Dw8rKysr/"},
{"skip":1},
{"data": "//8="},
{"skip":22},
{"data": "/8PKysrK/w=="},
{"skip":2},
{"data": "//85/w=="},
{"skip":17},
{"data": "/8PDyv8I//8="},
{"skip":27},
{"data": "/1lZWcrK/w=="},
{"skip":23},
{"data": "/wgP/8PKyv8="},
{"skip":21},
{"data": "/w85///DysO2tv8="},
{"skip":24},
{"data": "/7a2tsPKw/8="},
{"skip":1},
{"data": "//8="},
{"skip":22},
{"data": "/8PKysrD/3//"},
{"skip":20},
{"data": "/wj//8rKw8rD//8="},
{"skip":19},
{"data": "/w=="},
{"skip":4},
{"data": "/8rKw7a2/w=="},
{"skip":26},
{"data": "//8POf/Dtv//"},
{"skip":21},
{"data": "///KysrKysP/"},
{"skip":19},
{"data": "/wj/w8PDysrKw8PD/wj/"},
{"skip":19},
{"data": "////w8rKw8PDyv8="},
{"skip":21},
{"data": "/8rDw8rKysP///8="},
{"skip":23},
{"data": "/8rDysrKyv8="},
{"skip":24},
{"data": "///DysPKyv//CP8="},
{"skip":22},
{"data": "/7a2w8rK/w=="},
{"skip":3},
{"data": "//8="},
{"skip":17},
{"data": "//+2w/85D///"},
{"skip":26},
{"data": "/8PKysrK//8="},
{"skip":23},
{"data": "/w85/8PK//8="},
{"skip":22},
{"data": "////qv/Ktv///w=="},
{"skip":24},
{"data": "/////////3//"},
{"skip":24},
{"data": "/7bDw8P/qn//"},
{"skip":20},
{"data": "/w85/8rDw///f/8="},
{"skip":25},
{"data": "/8O2////"},
{"skip":26},
{"data": "/8r//8O2/3//"},
{"skip":21},
{"data": "/6r//8rKw8P/"},
{"skip":19},
{"data": "/w85/8rDysrKw8r/OQ//"},
{"skip":19},
{"data": "/8rKysrDw7a2yv8="},
{"skip":21},
{"data": "/8q2tsPKysrKyv8="},
{"skip":23},
{"data": "///Kw8PK/w=="},
{"skip":25},
{"data": "/3///8PDyv85D/8="},
{"skip":22},
{"data": "////tsP/"},
{"skip":23},
{"data": "/3//tsP//8r/"},
{"skip":26},
{"data": "/8PDysr/qn//"},
{"skip":22},
{"data": "////////f/8="},
{"skip":24},
{"data": "/6qq//9/f/8="},
{"skip":24},
{"data": "/6qq/w=="},
{"skip":1},
{"data": "/6p//w=="},
{"skip":23},
{"data": "/6r/trb//6qqf/8="},
{"skip":20},
{"data": "/////////6p//w=="},
{"skip":25},
{"data": "////f3//"},
{"skip":26},
{"data": "////////qn//"},
{"skip":21},
{"data": "/6r/"},
{"skip":1},
{"data": "/8O2tv8="},
{"skip":20},
{"data": "///////Kysr//////w=="},
{"skip":21},
{"data": "////w8q2////"},
{"skip":23},
{"data": "////tsrD////"},
{"skip":24},
{"data": "///DtrbD/w=="},
{"skip":25},
{"data": "/3+q/////////w=="},
{"skip":23},
{"data": "/39/////"},
{"skip":23},
{"data": "/3+q/////////w=="},
{"skip":25},
{"data": "/7a2w/8="},
{"skip":1},
{"data": "/3//"},
{"skip":23},
{"data": "/6p/f/9//w=="},
{"skip":23},
{"data": "/3+q/w=="},
{"skip":1},
{"data": "/6p/f/8="},
{"skip":22},
{"data": "/6qqqv8="},
{"skip":2},
{"data": "/6p//w=="},
{"skip":22},
{"data": "/6qq//8="},
{"skip":2},
{"data": "/6qq/w=="},
{"skip":22},
{"data": "/6p/f/+qf/8="},
{"skip":25},
{"data": "/6r/f3//"},
{"skip":25},
{"data": "/3+qqv8="},
{"skip":1},
{"data": "/6p//w=="},
{"skip":21},
{"data": "////"},
{"skip":2},
{"data": "/////w=="},
{"skip":22},
{"data": "/6qq////qqr/"},
{"skip":23},
{"data": "/6qq////f3//"},
{"skip":23},
{"data": "/39/////qqr/"},
{"skip":24},
{"data": "////////"},
{"skip":26},
{"data": "/3+q/39/qv8="},
{"skip":25},
{"data": "/39//6r/"},
{"skip":23},
{"data": "/3+q/w=="},
{"skip":2},
{"data": "/6qqf/8="},
{"skip":24},
{"data": "/////w=="},
{"skip":2},
{"data": "/6r/"},
{"skip":23},
{"data": "/6p/qv+q/w=="},
{"skip":23},
{"data": "/3+q/w=="},
{"skip":2},
{"data": "/6p//w=="},
{"skip":22},
{"data": "/3+q/w=="},
{"skip":3},
{"data": "/6qq/w=="},
{"skip":22},
{"data": "/3+q/w=="},
{"skip":3},
{"data": "/6qq/w=="},
{"skip":22},
{"data": "/6p/f/+qqv8="},
{"skip":24},
{"data": "/6qq/6p/f/8="},
{"skip":23},
{"data": "/3+q//8="},
{"skip":3},
{"data": "/6p//w=="},
{"skip":19},
{"data": "/4iI/w=="},
{"skip":2},
{"data": "/6p//w=="},
{"skip":22},
{"data": "/39//w=="},
{"skip":1},
{"data": "/39//w=="},
{"skip":24},
{"data": "/6r/"},
{"skip":1},
{"data": "/39//w=="},
{"skip":23},
{"data": "/39//w=="},
{"skip":1},
{"data": "/6qq/w=="},
{"skip":23},
{"data": "/4iI/6p//w=="},
{"skip":26},
{"data": "/6qq/6p/qv8="},
{"skip":24},
{"data": "/39/qv+qqv8="},
{"skip":21},
{"data": "/3+q/w=="},
{"skip":4},
{"data": "//+qf/8="},
{"skip":22},
{"data": "/39//w=="},
{"skip":1},
{"data": "//////8="},
{"skip":23},
{"data": "/6p//6r/"},
{"skip":23},
{"data": "/3+q/w=="},
{"skip":3},
{"data": "/6qq/w=="},
{"skip":21},
{"data": "/3+qqv8="},
{"skip":3},
{"data": "/6qq/w=="},
{"skip":21},
{"data": "/3+q/w=="},
{"skip":5},
{"data": "/6r/"},
{"skip":22},
{"data": "/6p///+q/w=="},
{"skip":24},
{"data": "/4j//w=="},
{"skip":1},
{"data": "/6qq/w=="},
{"skip":22},
{"data": "/////w=="},
{"skip":5},
{"data": "/6qq/w=="},
{"skip":18},
{"data": "/4iI//8="},
{"skip":3},
{"data": "/6qq/w=="},
{"skip":21},
{"data": "/39//w=="},
{"skip":1},
{"data": "/39//w=="},
{"skip":24},
{"data": "//+q//9/qv8="},
{"skip":23},
{"data": "/6p///+q//8="},
{"skip":24},
{"data": "/////6p/f/8="},
{"skip":26},
{"data": "/6r//3+q/w=="},
{"skip":24},
{"data": "/6qq/w=="},
{"skip":1},
{"data": "//+I/w=="},
{"skip":20},
{"data": "/6qq/w=="},
{"skip":6},
{"data": "/////w=="},
{"skip":21},
{"data": "/6qq/w=="},
{"skip":1},
{"data": "//+IiP8="},
{"skip":23},
{"data": "/6qq/////w=="},
{"skip":21},
{"data": "/4j//w=="},
{"skip":4},
{"data": "/6qq/w=="},
{"skip":21},
{"data": "/3+q/w=="},
{"skip":5},
{"data": "//////8="},
{"skip":19},
{"data": "/3+q/w=="},
{"skip":5},
{"data": "//////8="},
{"skip":20},
{"data": "/6qq//+q/w=="},
{"skip":25},
{"data": "/4iI//+qqv8="},
{"skip":22},
{"data": "/4iI/w=="},
{"skip":5},
{"data": "/6qq/w=="},
{"skip":18},
{"data": "////"},
{"skip":5},
{"data": "/6qq/w=="},
{"skip":21},
{"data": "/6p//w=="},
{"skip":1},
{"data": "/3+q/w=="},
{"skip":24},
{"data": "/4j/"},
{"skip":1},
{"data": "/3//"},
{"skip":25},
{"data": "/3//"},
{"skip":1},
{"data": "/4j/"},
{"skip":27},
{"data": "//+qf/8="},
{"skip":26},
{"data": "/6r//6qq/w=="},
{"skip":24},
{"data": "/6qq//+IiP8="},
{"skip":21},
{"data": "/6qq/w=="},
{"skip":6},
{"data": "/4iI/w=="},
{"skip":21},
{"data": "/6qq/w=="},
{"skip":3},
{"data": "////"},
{"skip":23},
{"data": "/6qq/4iIiP8="},
{"skip":20},
{"data": "/4iIiP8="},
{"skip":3},
{"data": "/6qq/w=="},
{"skip":20},
{"data": "/3+q/w=="},
{"skip":6},
{"data": "/4iIiIj/"},
{"skip":17},
{"data": "/3+q/w=="},
{"skip":6},
{"data": "/4iIiIj/"},
{"skip":19},
{"data": "/6r/"},
{"skip":1},
{"data": "/////w=="},
{"skip":25},
{"data": "/////6qq/w=="},
{"skip":23},
{"data": "/4iI/w=="},
{"skip":4},
{"data": "/6qq/w=="},
{"skip":27},
{"data": "/6r/"},
{"skip":21},
{"data": "/6qq/w=="},
{"skip":1},
{"data": "/6qq/w=="},
{"skip":24},
{"data": "//8="},
{"skip":1},
{"data": "/6p//w=="},
{"skip":25},
{"data": "/3+q/w=="},
{"skip":1},
{"data": "//8="},
{"skip":28},
{"data": "/6p//w=="},
{"skip":25},
{"data": "/////w=="},
{"skip":1},
{"data": "/6r/"},
{"skip":24},
{"data": "/6qq/////w=="},
{"skip":22},
{"data": "/6qq/w=="},
{"skip":5},
{"data": "/4iI/w=="},
{"skip":22},
{"data": "/6r/"},
{"skip":30},
{"data": "//////////8="},
{"skip":21},
{"data": "/////w=="},
{"skip":3},
{"data": "/6r//w=="},
{"skip":19},
{"data": "/4j//w=="},
{"skip":8},
{"data": "//////8="},
{"skip":17},
{"data": "/6r/"},
{"skip":7},
{"data": "////////"},
{"skip":19},
{"data": "////"},
{"skip":1},
{"data": "//+IiP8="},
{"skip":28},
{"data": "////"},
{"skip":24},
{"data": "////"},
{"skip":5},
{"data": "/6r/"},
{"skip":27},
{"data": "////"},
{"skip":21},
{"data": "//+q/w=="},
{"skip":1},
{"data": "/6r//w=="},
{"skip":27},
{"data": "/6p//w=="},
{"skip":25},
{"data": "/3+q/w=="},
{"skip":31},
{"data": "/6r//w=="},
{"skip":24},
{"data": "/4iI//8="},
{"skip":1},
{"data": "////"},
{"skip":24},
{"data": "////"},
{"skip":26},
{"data": "/6r/"},
{"skip":6},
{"data": "////"},
{"skip":23},
{"data": "////"},
{"skip":30},
{"data": "/4iI//8="},
{"skip":32},
{"data": "/4iI//8="},
{"skip":17},
{"data": "/4iI//8="},
{"skip":28},
{"data": "/4j///8="},
{"skip":31},
{"data": "/4iI/w=="},
{"skip":2},
{"data": "////"},
{"skip":28},
{"data": "/4iI/w=="},
{"skip":31},
{"data": "/////w=="},
{"skip":26},
{"data": "/4iI/w=="},
{"skip":20},
{"data": "/4j//w=="},
{"skip":1},
{"data": "//+I/w=="},
{"skip":27},
{"data": "//////8="},
{"skip":24},
{"data": "/////w=="},
{"skip":31},
{"data": "//+I/w=="},
{"skip":24},
{"data": "////"},
{"skip":2},
{"data": "/4iI/w=="},
{"skip":23},
{"data": "/4iI/w=="},
{"skip":25},
{"data": "/////w=="},
{"skip":31},
{"data": "/4iI/w=="},
{"skip":30},
{"data": "/4iIiIj/"},
{"skip":31},
{"data": "/4iIiIj/"},
{"skip":17},
{"data": "/4iIiP8="},
{"skip":27},
{"data": "/4iIiIj/"},
{"skip":30},
{"data": "/4iIiP8="},
{"skip":32},
{"data": "/4iIiP8="},
{"skip":30},
{"data": "//+IiP8="},
{"skip":25},
{"data": "/4iIiP8="},
{"skip":19},
{"data": "/4iI/w=="},
{"skip":1},
{"data": "/4iI/w=="},
{"skip":27},
{"data": "/4iIiP8="},
{"skip":23},
{"data": "/4iIiP8="},
{"skip":31},
{"data": "/4iIiP8="},
{"skip":27},
{"data": "/4iIiP8="},
{"skip":22},
{"data": "/4iIiP8="},
{"skip":24},
{"data": "/4iI//8="},
{"skip":30},
{"data": "/4iIiP8="},
{"skip":30},
{"data": "////////"},
{"skip":31},
{"data": "////////"},
{"skip":18},
{"data": "/////w=="},
{"skip":27},
{"data": "////////"},
{"skip":31},
{"data": "/////w=="},
{"skip":33},
{"data": "/////w=="},
{"skip":32},
{"data": "////"},
{"skip":26},
{"data": "/////w=="},
{"skip":19},
{"data": "////"},
{"skip":3},
{"data": "////"},
{"skip":27},
{"data": "//////8="},
{"skip":23},
{"data": "//////8="},
{"skip":32},
{"data": "/////w=="},
{"skip":27},
{"data": "/////w=="},
{"skip":23},
{"data": "/////w=="},
{"skip":25},
{"data": "////"},
{"skip":32},
{"data": "/////w=="},
{"skip":31},
{"data": "//////8="},
{"skip":27},
{"data": "/////w=="},
{"skip":29},
{"data": "/////w=="},
{"skip":58},
{"data": "//////8="},
{"skip":27},
{"data": "/////w=="},
{"skip":29},
{"data": "//////8="},
{"skip":59},
{"data": "//////8="},
{"skip":125},
{"data": "//////8="},
{"skip":28},
{"data": "/////w=="},
{"skip":26},
{"data": "//////8="},
{"skip":56},
{"data": "//+sgYGBrP8="},
{"skip":24},
{"data": "//+BgYGs//8="},
{"skip":26},
{"data": "/6yBgaz//w=="},
{"skip":25},
{"data": "//////8="},
{"skip":24},
{"data": "//+BgYGBrP8="},
{"skip":24},
{"data": "//+BgYGB//8="},
{"skip":26},
{"data": "/4GBgYGs/w=="},
{"skip":25},
{"data": "//////8="},
{"skip":27},
{"data": "/6yBgYGs/w=="},
{"skip":26},
{"data": "//////8="},
{"skip":27},
{"data": "//////8="},
{"skip":60},
{"data": "/6yBgYGB//8="},
{"skip":24},
{"data": "//+BgYGB//8="},
{"skip":23},
{"data": "/6yBgYGB/w=="},
{"skip":27},
{"data": "//////8="},
{"skip":6},
{"data": "/w=="},
{"skip":17},
{"data": "/6ysgYGB/w=="},
{"skip":24},
{"data": "/6ysrIGBgaz/"},
{"skip":25},
{"data": "/6ysgYGBrP8="},
{"skip":22},
{"data": "//+sgYGBrP8="},
{"skip":24},
{"data": "/6ys/4GB/w=="},
{"skip":24},
{"data": "/6ysrP+Bgaz/"},
{"skip":25},
{"data": "/6z/gYGBrP8="},
{"skip":16},
{"data": "//8="},
{"skip":5},
{"data": "/4GBgYGs/w=="},
{"skip":26},
{"data": "/4GBgYGB/w=="},
{"skip":25},
{"data": "/6yBgYGs/w=="},
{"skip":24},
{"data": "//+sgYGBrP8="},
{"skip":22},
{"data": "//8="},
{"skip":3},
{"data": "/////w=="},
{"skip":28},
{"data": "/4GB/6ys/w=="},
{"skip":24},
{"data": "/6yBgf+srKz/"},
{"skip":22},
{"data": "/6yBgYH/rP8="},
{"skip":26},
{"data": "/6yBgYGs/w=="},
{"skip":4},
{"data": "/zn/"},
{"skip":17},
{"data": "//+s/4Gs/w=="},
{"skip":23},
{"data": "/6z//6z/gYH/"},
{"skip":25},
{"data": "//+s/6yB/w=="},
{"skip":24},
{"data": "/6ysgYGB/w=="},
{"skip":25},
{"data": "//8P/4Gs/w=="},
{"skip":23},
{"data": "/6z//w//gYH/"},
{"skip":25},
{"data": "//8P/4GB/w=="},
{"skip":16},
{"data": "/wgI/w=="},
{"skip":4},
{"data": "/6ys/4GBrP8="},
{"skip":25},
{"data": "/4GBrIGs/w=="},
{"skip":25},
{"data": "/4GBgYGBrP8="},
{"skip":22},
{"data": "/6yBrIGBgYH/"},
{"skip":21},
{"data": "/w8P/w=="},
{"skip":1},
{"data": "/6yBgaz/"},
{"skip":26},
{"data": "/6yB/w///w=="},
{"skip":25},
{"data": "/4GB/w///6z/"},
{"skip":23},
{"data": "/4GB/w///w=="},
{"skip":26},
{"data": "/4GB/6ys/w=="},
{"skip":3},
{"data": "//8P/w=="},
{"skip":17},
{"data": "/zn/D/+B/w=="},
{"skip":24},
{"data": "//85/w//gf8="},
{"skip":25},
{"data": "/zn/D/+sgf8="},
{"skip":24},
{"data": "//+s/4Gs/w=="},
{"skip":24},
{"data": "/wg5/4GB//8="},
{"skip":23},
{"data": "//8IOf+sgf8="},
{"skip":25},
{"data": "/wg5/6yBrP8="},
{"skip":15},
{"data": "/w8P//8="},
{"skip":4},
{"data": "//8P/4GB/w=="},
{"skip":24},
{"data": "/6yBrIGsgaz/"},
{"skip":24},
{"data": "/6yBgYGBgf8="},
{"skip":23},
{"data": "/6yBgYGBrP8="},
{"skip":21},
{"data": "/zn///+sgYGBgf8="},
{"skip":25},
{"data": "//+Bgf85CP8="},
{"skip":25},
{"data": "/4Gs/zkI//8="},
{"skip":23},
{"data": "/6yBrP85CP8="},
{"skip":25},
{"data": "/6yB/w///w=="},
{"skip":3},
{"data": "/7bK/w=="},
{"skip":18},
{"data": "/wgIOf+BrP8="},
{"skip":24},
{"data": "/wgIOf+s/w=="},
{"skip":25},
{"data": "/wgIOf+s/w=="},
{"skip":25},
{"data": "/zn/D/+B/w=="},
{"skip":24},
{"data": "/w//rKyB/7b/"},
{"skip":23},
{"data": "/w//Of+B//8="},
{"skip":24},
{"data": "/w//rIGs////"},
{"skip":15},
{"data": "///Ktv//////CDn/rIH/"},
{"skip":24},
{"data": "/4GBgaysgaz/"},
{"skip":24},
{"data": "/6yBrIGsgaz/"},
{"skip":21},
{"data": "/6yBrIGsgaz/"},
{"skip":22},
{"data": "/7b//4GBgYGB/w=="},
{"skip":24},
{"data": "/7b/gays/w//"},
{"skip":24},
{"data": "//+B/zn/D/8="},
{"skip":23},
{"data": "////rIGs/w//"},
{"skip":25},
{"data": "/4GB/zkI/////7bK/w=="},
{"skip":19},
{"data": "/zkP/w////8="},
{"skip":23},
{"data": "//85D/+s//8="},
{"skip":25},
{"data": "/zkP/w///w=="},
{"skip":15},
{"data": "////"},
{"skip":7},
{"data": "/wgI/6yBrP8="},
{"skip":23},
{"data": "/zn/rIGsgf//"},
{"skip":23},
{"data": "/zn///+s//8="},
{"skip":24},
{"data": "/zn/gays/8O2/w=="},
{"skip":16},
{"data": "/8O2tsPD////rIGs/w=="},
{"skip":1},
{"data": "/w=="},
{"skip":20},
{"data": "////rIGsrIGsrP///w=="},
{"skip":22},
{"data": "/6ysgayBrKz/"},
{"skip":21},
{"data": "/4GsgayBrP8="},
{"skip":23},
{"data": "/8P/rIGsgYH/"},
{"skip":25},
{"data": "//+BrIGs/zn/"},
{"skip":24},
{"data": "//+s////Of8="},
{"skip":22},
{"data": "/7a2/6ysgf85/w=="},
{"skip":25},
{"data": "/4Gs//8P/8PDw8r/"},
{"skip":20},
{"data": "/w//Of+2w/8="},
{"skip":23},
{"data": "//8P/zn/trb/"},
{"skip":24},
{"data": "/w/////DL/8="},
{"skip":13},
{"data": "/wgP//8="},
{"skip":6},
{"data": "/zkP/4GB////"},
{"skip":23},
{"data": "////rIH///8="},
{"skip":24},
{"data": "//+2tv8v/w=="},
{"skip":23},
{"data": "////tv+B/8Mv//8="},
{"skip":17},
{"data": "/8PDw8O2tv+BrKz//zn/"},
{"skip":18},
{"data": "/7a2tv+s//+s//9Ztrb/"},
{"skip":21},
{"data": "//+BrIH/rIH//w=="},
{"skip":19},
{"data": "//+srP+s/////w=="},
{"skip":23},
{"data": "//+srIGB//8="},
{"skip":2},
{"data": "/w=="},
{"skip":22},
{"data": "/8P/gaz///8="},
{"skip":25},
{"data": "/8P/w8P//w=="},
{"skip":23},
{"data": "///Dtv+B/8P///8="},
{"skip":24},
{"data": "////D/85/8PD//8="},
{"skip":22},
{"data": "/zn/tra2/w=="},
{"skip":23},
{"data": "////Of/Dtra2/w=="},
{"skip":24},
{"data": "//+2tsMvw/8="},
{"skip":12},
{"data": "/wg5/8P/"},
{"skip":3},
{"data": "////////gaz/L7b/"},
{"skip":21},
{"data": "/7a2tv//wy//"},
{"skip":24},
{"data": "/7a2tsMv/w=="},
{"skip":22},
{"data": "/7a2tra2/8PDL///"},
{"skip":18},
{"data": "////w8O2tv+B/y////8="},
{"skip":18},
{"data": "/8O2trb/w///wy9ZtsP/"},
{"skip":19},
{"data": "//+2w////8r//8P/"},
{"skip":19},
{"data": "/8P//8P//8MvWf//"},
{"skip":21},
{"data": "/8P/gaz/L1n//w//"},
{"skip":21},
{"data": "/8PD//8vWVn/"},
{"skip":24},
{"data": "/8PDwy9Z/w=="},
{"skip":23},
{"data": "///Dw8P/w8MvWbb/"},
{"skip":22},
{"data": "/y/Dtv85/8PK/w=="},
{"skip":23},
{"data": "/8P/w8O2tv8="},
{"skip":22},
{"data": "/8P/L//Dw8O2tv8="},
{"skip":24},
{"data": "/7a2tsMv//8="},
{"skip":13},
{"data": "///Dw7b////Dw8O2trb//y9Zw8P/"},
{"skip":19},
{"data": "/7a2tsPDwy9Z//8="},
{"skip":22},
{"data": "/7a2tsPDL/8="},
{"skip":22},
{"data": "/7a2w8PDw8MvWf/D/w=="},
{"skip":20},
{"data": "/8PDw8P/L1m2/8r/"},
{"skip":17},
{"data": "/8PDw8PDw8PDL1nKw8P/"},
{"skip":18},
{"data": "/7a2tsPDw8PDL8rK/w=="},
{"skip":19},
{"data": "/8rKw8PDwy9Ztra2/w=="},
{"skip":20},
{"data": "/8r/rP8vWcq2////"},
{"skip":20},
{"data": "///Kw8MvWba2tv8="},
{"skip":23},
{"data": "/8PDL1m2tv8="},
{"skip":21},
{"data": "/8P/w8PDw8MvWba2/w=="},
{"skip":21},
{"data": "/7ZZ////Of/D/w=="},
{"skip":24},
{"data": "/8PDw8rDw/8="},
{"skip":22},
{"data": "/8P/L8PDw8PDw/8="},
{"skip":24},
{"data": "/8PDw8Mv//8="},
{"skip":15},
{"data": "///DtsPKw8PDw8PDw8MvysrDw/8="},
{"skip":18},
{"data": "/8PDw8PDwy/K//8="},
{"skip":22},
{"data": "/7a2w8PDL/8="},
{"skip":22},
{"data": "/8PDw8PDw8Mvyv/D/w=="},
{"skip":20},
{"data": "/8PDw8MvWcrDtv//"},
{"skip":17},
{"data": "/8P/ysPDw8MvWcrD/8P/"},
{"skip":18},
{"data": "/8O2w8PDw8MvWcr/w/8="},
{"skip":17},
{"data": "/8P/ysPDwy9ZysO2w/8="},
{"skip":21},
{"data": "////L1nKtrb/yv8="},
{"skip":20},
{"data": "///Kwy9ZysPDw/8="},
{"skip":23},
{"data": "/8MvWcq2tv8="},
{"skip":21},
{"data": "/8P/ysPDwy9ZysPD/w=="},
{"skip":21},
{"data": "/8P/CA///8PK/w=="},
{"skip":24},
{"data": "/y/Dyv/Dw/8="},
{"skip":22},
{"data": "/8P/L8PDw//Dw8r/"},
{"skip":23},
{"data": "/8PDyi9Z/8P/"},
{"skip":16},
{"data": "///KysrKw8PDw8MvWf//ysP/"},
{"skip":18},
{"data": "/8PDw8PDwy//w/8="},
{"skip":22},
{"data": "/8PDw8MvWf8="},
{"skip":22},
{"data": "/8PD/8PDwy9Z///D/w=="},
{"skip":20},
{"data": "/8rDwy9ZysPKw8O2/w=="},
{"skip":16},
{"data": "/8P/ysPDwy9ZysPK/8P/"},
{"skip":18},
{"data": "/7bDw8PDw8Mvysr/w/8="},
{"skip":17},
{"data": "/8P/ysrDL1nKw8PDtv8="},
{"skip":21},
{"data": "/8MvWcrDtsPD//8="},
{"skip":20},
{"data": "/8P/wy/Kw8PDw/8="},
{"skip":23},
{"data": "/8NZysPDw/8="},
{"skip":21},
{"data": "/8P//8PDL1nK/8PD/w=="},
{"skip":20},
{"data": "/7b///8P/8PD/w=="},
{"skip":25},
{"data": "/y/Dyv/Dw/8="},
{"skip":21},
{"data": "/7bD/1kvw8PK/8PD/w=="},
{"skip":22},
{"data": "/8PDw8ovyv/D/w=="},
{"skip":18},
{"data": "/////8rDw8PDL8r/"},
{"skip":1},
{"data": "//8="},
{"skip":19},
{"data": "/8PDysPDL1n/w/8="},
{"skip":22},
{"data": "/8PDw8Mvyv8="},
{"skip":21},
{"data": "/8PDw//Dw8Mvyv//w8r/"},
{"skip":19},
{"data": "/8rDL1nKw8r/ysPD/w=="},
{"skip":16},
{"data": "/8PK/8PDL1nKysP/ysP/"},
{"skip":18},
{"data": "/7bDysPDwy9Zyv/Kw/8="},
{"skip":17},
{"data": "/8PK/8ovWcrDw8rDtv8="},
{"skip":21},
{"data": "/y9ZysPKw8PDtv8="},
{"skip":20},
{"data": "/8P/L1nKw8rDw/8="},
{"skip":23},
{"data": "/y/Kw8PDw/8="},
{"skip":20},
{"data": "/8rD///DL1nKw//Dw8P/"},
{"skip":19},
{"data": "//+2trb/L8PD/w=="},
{"skip":25},
{"data": "/1kvw//Dw/8="},
{"skip":21},
{"data": "/7bK/8ovw8PK/8PD/w=="},
{"skip":22},
{"data": "/8PD/y9Zyv/D/w=="},
{"skip":22},
{"data": "/8PDwy9Zyv8="},
{"skip":22},
{"data": "/8PD/8rDL8r/yv8="},
{"skip":22},
{"data": "/8PDw/8vyv8="},
{"skip":21},
{"data": "/8PD/8rDwy9Zyv//ysP/"},
{"skip":19},
{"data": "/8ovWcrDyv8="},
{"skip":1},
{"data": "////"},
{"skip":17},
{"data": "/8PD/8ovWcrKw8r/w8P/"},
{"skip":17},
{"data": "/8O2w//Dwy9ZysP/ysP/"},
{"skip":17},
{"data": "/8PK/y9ZysPDw//DtsP/"},
{"skip":20},
{"data": "/1nKw8rD/8PDtv8="},
{"skip":20},
{"data": "/8r/L8rDyv/Dw/8="},
{"skip":23},
{"data": "/1nK/8PDw/8="},
{"skip":20},
{"data": "/8PK//8vWcrDw8r/w8P/"},
{"skip":19},
{"data": "/7a2w//KWS/D/w=="},
{"skip":25},
{"data": "/8ovw//Dw/8="},
{"skip":20},
{"data": "/7bD///KWS/Dyv/Dw/8="},
{"skip":22},
{"data": "/8PD/1nKyv/Dw/8="},
{"skip":21},
{"data": "/8rDL1nK/w=="},
{"skip":23},
{"data": "/8PD/8ovWcr//w=="},
{"skip":23},
{"data": "///Dw/9Zyv8="},
{"skip":20},
{"data": "/8PKyv/Kwy9Zysr/"},
{"skip":1},
{"data": "/8P/"},
{"skip":19},
{"data": "/y9ZysPKyv8="},
{"skip":21},
{"data": "/8PD/y9ZysrDysr/w8P/"},
{"skip":17},
{"data": "/7bDyv/KL1nKw8r///8="},
{"skip":19},
{"data": "////WcrDysPK/8rDtv8="},
{"skip":20},
{"data": "/8rDysPK///Kyv8="},
{"skip":21},
{"data": "//9ZysPK/8PD/w=="},
{"skip":23},
{"data": "/8rK/8PD//8="},
{"skip":20},
{"data": "/8P/"},
{"skip":1},
{"data": "/1nKw8rDyv/KysP/"},
{"skip":18},
{"data": "/8PD/8rDylkv/w=="},
{"skip":25},
{"data": "/8pZL//Dtv8="},
{"skip":20},
{"data": "////"},
{"skip":1},
{"data": "/8PKWS/K///D/w=="},
{"skip":21},
{"data": "/8O2/1kvL/8="},
{"skip":1},
{"data": "/8P/"},
{"skip":21},
{"data": "/8ovWcrK/w=="},
{"skip":23},
{"data": "/8PD/y9Zyi///w=="},
{"skip":22},
{"data": "/8P/w8P/yi//"},
{"skip":20},
{"data": "/8rK/w=="},
{"skip":1},
{"data": "/y9Zysov/w=="},
{"skip":1},
{"data": "////"},
{"skip":19},
{"data": "/1nKw8rD/w=="},
{"skip":22},
{"data": "/8rD/1nKysrKysr/w8r/"},
{"skip":17},
{"data": "/8rK//9ZWcrDysr/"},
{"skip":23},
{"data": "/8rKysPKyv//ysr/"},
{"skip":20},
{"data": "/y/Kw8rK/w=="},
{"skip":1},
{"data": "//8="},
{"skip":22},
{"data": "//8vysPD/8PD/w=="},
{"skip":23},
{"data": "/y/K/8PD/8P/"},
{"skip":19},
{"data": "////"},
{"skip":1},
{"data": "/y/KysPK/w=="},
{"skip":1},
{"data": "/8rK/w=="},
{"skip":18},
{"data": "////ysPKw8pZ/w=="},
{"skip":25},
{"data": "/8rKWf+2tv8="},
{"skip":19},
{"data": "/wgP/w=="},
{"skip":2},
{"data": "/y/KWS///8PD/w=="},
{"skip":20},
{"data": "/7bD/y9ZWf8="},
{"skip":1},
{"data": "//85/w=="},
{"skip":20},
{"data": "/y9ZysrK/w=="},
{"skip":23},
{"data": "/8PK/1nKL1n/"},
{"skip":22},
{"data": "/w///8PD/y9Z/w=="},
{"skip":18},
{"data": "///Kyv8="},
{"skip":2},
{"data": "/1nKyi9Z/w=="},
{"skip":1},
{"data": "/zn/"},
{"skip":19},
{"data": "/y/KysrK/w=="},
{"skip":22},
{"data": "/8rK/y8vLy8vLy//ysr/"},
{"skip":17},
{"data": "/8rK//8vL8rKysr/"},
{"skip":23},
{"data": "/8rKysovL///ysr/"},
{"skip":20},
{"data": "/1kvL8rK/w=="},
{"skip":26},
{"data": "/1kvysr/ysP/"},
{"skip":23},
{"data": "/1kv/8PD//8P/w=="},
{"skip":18},
{"data": "/zn/"},
{"skip":1},
{"data": "/1kvysrK/w=="},
{"skip":2},
{"data": "/8rK//8="},
{"skip":19},
{"data": "/8rDysov/w=="},
{"skip":26},
{"data": "/y8v/7a2/w=="},
{"skip":19},
{"data": "/wj/"},
{"skip":3},
{"data": "/1kvL1n//8PD/w=="},
{"skip":18},
{"data": "//+2w/9ZWcrK/w=="},
{"skip":1},
{"data": "/w8I/w=="},
{"skip":20},
{"data": "/1nKyi8v/w=="},
{"skip":22},
{"data": "/8PK/y8vL1nKw/8="},
{"skip":21},
{"data": "/zn////Dw//K/w=="},
{"skip":17},
{"data": "/wgP//8="},
{"skip":3},
{"data": "/y8vL1nK//8PCP8="},
{"skip":19},
{"data": "/1kvLy8v/w=="},
{"skip":22},
{"data": "/8rK/1lZWVlZWVn/ysr/"},
{"skip":17},
{"data": "////"},
{"skip":1},
{"data": "/1lZLy8vL/8="},
{"skip":23},
{"data": "/y8vLy9ZWf8="},
{"skip":1},
{"data": "/8r/"},
{"skip":20},
{"data": "/8pZWS8v/w=="},
{"skip":25},
{"data": "/8PKWS8vL//Kw/8="},
{"skip":22},
{"data": "/8r/w8P///85/w=="},
{"skip":18},
{"data": "/wgP///KWS8vL/8="},
{"skip":3},
{"data": "//8PCP8="},
{"skip":18},
{"data": "/8rKyi9Z/w=="},
{"skip":26},
{"data": "/1lZ/7bD/w=="},
{"skip":20},
{"data": "/w=="},
{"skip":4},
{"data": "/8pZWcr/"},
{"skip":1},
{"data": "////"},
{"skip":17},
{"data": "/wj/w//KysrDyv8="},
{"skip":2},
{"data": "//8="},
{"skip":21},
{"data": "/y8vL1lZ/w=="},
{"skip":22},
{"data": "/8rK/1lZWcrDyv8="},
{"skip":22},
{"data": "///K/8PD/8P/"},
{"skip":17},
{"data": "/zkI/w=="},
{"skip":3},
{"data": "//9ZWVnK/w=="},
{"skip":2},
{"data": "//8="},
{"skip":20},
{"data": "/8pZWVlZ/w=="},
{"skip":22},
{"data": "/8r//8rKysrKysr//8r/"},
{"skip":16},
{"data": "/wg5///DyspZWVlZ/w=="},
{"skip":23},
{"data": "/1lZWVnKysP///8P/w=="},
{"skip":19},
{"data": "/8PKyllZ/w=="},
{"skip":25},
{"data": "/8rDyllZWf/Kyv8="},
{"skip":22},
{"data": "/8P/w8P/yv//"},
{"skip":20},
{"data": "///////KWVlZ//8="},
{"skip":3},
{"data": "/wg5/w=="},
{"skip":18},
{"data": "/y8vL1nKw/8="},
{"skip":24},
{"data": "/8PKyv////8="},
{"skip":24},
{"data": "/8PDysrKw/8PCP8="},
{"skip":17},
{"data": "/w85///KysrDw/8="},
{"skip":25},
{"data": "/1lZWcrKyv8="},
{"skip":21},
{"data": "///K/8rKysrDw/8="},
{"skip":23},
{"data": "/8r/w8P/w8r/"},
{"skip":17},
{"data": "//8="},
{"skip":4},
{"data": "/8rKysrK/w=="},
{"skip":23},
{"data": "/8PKysrKysr/"},
{"skip":21},
{"data": "////ysrDw8PDysrK////"},
{"skip":17},
{"data": "/w///8PKysrKysr/"},
{"skip":23},
{"data": "/8rKysrKysP//zkP/w=="},
{"skip":20},
{"data": "/8rDysrK/w=="},
{"skip":24},
{"data": "/8PDysrKyv/K//8="},
{"skip":21},
{"data": "/8rD/8PD/8r/"},
{"skip":25},
{"data": "/8rKysrK/w=="},
{"skip":4},
{"data": "//8="},
{"skip":19},
{"data": "/1lZWcrKyv8="},
{"skip":24},
{"data": "/8rKw/8PCP8="},
{"skip":24},
{"data": "/7a2w8rD//85D/8="},
{"skip":18},
{"data": "//8="},
{"skip":1},
{"data": "/8PKw7a2tv8="},
{"skip":24},
{"data": "/8rKysrKw/8="},
{"skip":21},
{"data": "/wj//8rKw8rD/w=="},
{"skip":24},
{"data": "/8P////Kw7b/"},
{"skip":23},
{"data": "/8rKw8r/"},
{"skip":24},
{"data": "/8PKysrKw8P/"},
{"skip":21},
{"data": "/wj/ysPDw8PDw8rD/wj/"},
{"skip":18},
{"data": "////ysrKysPDw8r/"},
{"skip":21},
{"data": "/8rDw8PKysrK/w=="},
{"skip":1},
{"data": "//8="},
{"skip":21},
{"data": "/8rDw8PK/w=="},
{"skip":25},
{"data": "/8PKw8rK//8I/w=="},
{"skip":21},
{"data": "/7bDyv///8P/"},
{"skip":26},
{"data": "/8rDysr/"},
{"skip":25},
{"data": "/8rKysrK//8="},
{"skip":24},
{"data": "///Kw/85D/8="},
{"skip":24},
{"data": "////tsr/qv///w=="},
{"skip":21},
{"data": "/3//////////"},
{"skip":23},
{"data": "/7bDw8rKyv//"},
{"skip":21},
{"data": "/w85/8PDyv///w=="},
{"skip":23},
{"data": "/3///zn//////w=="},
{"skip":23},
{"data": "/8rDtsP/"},
{"skip":23},
{"data": "/3//w8rKw7a2/w=="},
{"skip":22},
{"data": "/w///8PDysPK//85D/8="},
{"skip":20},
{"data": "////ysPDtrbD/w=="},
{"skip":21},
{"data": "/8O2tsPDyv///w=="},
{"skip":24},
{"data": "///KtrbD/w=="},
{"skip":25},
{"data": "////ysPD/zkP/w=="},
{"skip":21},
{"data": "//////85//9//w=="},
{"skip":25},
{"data": "/8O2w8r/"},
{"skip":24},
{"data": "/8PDw8PK/6r/"},
{"skip":24},
{"data": "/3////////8="},
{"skip":24},
{"data": "/39///+qqv8="},
{"skip":23},
{"data": "/3+q/w=="},
{"skip":1},
{"data": "/6qq/w=="},
{"skip":23},
{"data": "//+2tsP//6qq/w=="},
{"skip":21},
{"data": "/////////3//"},
{"skip":23},
{"data": "/3+q/w8I/6qq/w=="},
{"skip":24},
{"data": "/////w=="},
{"skip":24},
{"data": "/6qq////////qv8="},
{"skip":22},
{"data": "//+q//////+q////"},
{"skip":21},
{"data": "/6qq////////"},
{"skip":23},
{"data": "////////qqr/"},
{"skip":24},
{"data": "/6r/////"},
{"skip":26},
{"data": "/3//////////"},
{"skip":22},
{"data": "/6qq/wgP/6p//w=="},
{"skip":26},
{"data": "/////w=="},
{"skip":25},
{"data": "/7a2tv///6r/"},
{"skip":24},
{"data": "/3//f3+q/w=="},
{"skip":24},
{"data": "/39/qv8="},
{"skip":1},
{"data": "/6p//w=="},
{"skip":21},
{"data": "/3+q/w=="},
{"skip":2},
{"data": "/6qqqv8="},
{"skip":21},
{"data": "/39/////"},
{"skip":1},
{"data": "/6p//w=="},
{"skip":23},
{"data": "/3+qqv+qf/8="},
{"skip":21},
{"data": "/3+q/w=="},
{"skip":1},
{"data": "////qqr/"},
{"skip":22},
{"data": "////qqr/"},
{"skip":24},
{"data": "/6r/"},
{"skip":4},
{"data": "/6qq/w=="},
{"skip":23},
{"data": "/6qq/w=="},
{"skip":1},
{"data": "/6qq/w=="},
{"skip":23},
{"data": "/6qq/w=="},
{"skip":1},
{"data": "/6qq/w=="},
{"skip":23},
{"data": "/6qq/w=="},
{"skip":1},
{"data": "/6qq/w=="},
{"skip":24},
{"data": "////qqr/"},
{"skip":25},
{"data": "/3+q/6qqf/8="},
{"skip":24},
{"data": "/6qq////"},
{"skip":1},
{"data": "/6p//w=="},
{"skip":25},
{"data": "/6qq////"},
{"skip":23},
{"data": "/////w=="},
{"skip":2},
{"data": "/6r///8="},
{"skip":22},
{"data": "/6r/qn+q/w=="},
{"skip":24},
{"data": "/3+q/w=="},
{"skip":2},
{"data": "/6p//w=="},
{"skip":21},
{"data": "/6qq/w=="},
{"skip":3},
{"data": "/6p//w=="},
{"skip":21},
{"data": "/3+q/w=="},
{"skip":4},
{"data": "/6p//w=="},
{"skip":22},
{"data": "/3+q//+qqv8="},
{"skip":21},
{"data": "/6qq/w=="},
{"skip":4},
{"data": "/6qq/w=="},
{"skip":21},
{"data": "/4j/qqr/"},
{"skip":23},
{"data": "/6qq/w=="},
{"skip":5},
{"data": "/6qq/w=="},
{"skip":22},
{"data": "/6qq/w=="},
{"skip":1},
{"data": "/6qq/w=="},
{"skip":23},
{"data": "/6qq/w=="},
{"skip":1},
{"data": "/6qq/w=="},
{"skip":23},
{"data": "/6qq/w=="},
{"skip":1},
{"data": "/6qq/w=="},
{"skip":24},
{"data": "/4j/qqr/"},
{"skip":25},
{"data": "/6qq//+qf/8="},
{"skip":23},
{"data": "/6qq/w=="},
{"skip":4},
{"data": "/6qq/w=="},
{"skip":25},
{"data": "/6qq/4j/"},
{"skip":23},
{"data": "/6qq/w=="},
{"skip":2},
{"data": "//+IiP8="},
{"skip":23},
{"data": "/6r/f6r/"},
{"skip":24},
{"data": "/6qq/w=="},
{"skip":3},
{"data": "/6p//w=="},
{"skip":20},
{"data": "/6qq/w=="},
{"skip":3},
{"data": "/6qqf/8="},
{"skip":20},
{"data": "/6qq/w=="},
{"skip":4},
{"data": "/6qqf/8="},
{"skip":21},
{"data": "/3+q/w=="},
{"skip":1},
{"data": "/6r/"},
{"skip":19},
{"data": "////qqr/"},
{"skip":4},
{"data": "/6p//w=="},
{"skip":22},
{"data": "/4j/qn//"},
{"skip":20},
{"data": "////qqr/"},
{"skip":5},
{"data": "/6p//w=="},
{"skip":22},
{"data": "/3+q/w=="},
{"skip":1},
{"data": "/6p//w=="},
{"skip":23},
{"data": "/////w=="},
{"skip":2},
{"data": "/3//"},
{"skip":23},
{"data": "/3//"},
{"skip":2},
{"data": "/////w=="},
{"skip":24},
{"data": "//8="},
{"skip":1},
{"data": "/3//"},
{"skip":25},
{"data": "/6r/"},
{"skip":1},
{"data": "/6p//w=="},
{"skip":23},
{"data": "/3+q/w=="},
{"skip":4},
{"data": "/6qq////"},
{"skip":22},
{"data": "/3+q/4j/"},
{"skip":24},
{"data": "/3//"},
{"skip":3},
{"data": "/4iI/w=="},
{"skip":23},
{"data": "/////6qq/w=="},
{"skip":24},
{"data": "/6qq/w=="},
{"skip":4},
{"data": "//+I/w=="},
{"skip":17},
{"data": "//////8="},
{"skip":5},
{"data": "/6p//w=="},
{"skip":20},
{"data": "/6qq/w=="},
{"skip":5},
{"data": "/6qq/w=="},
{"skip":21},
{"data": "/6qq/w=="},
{"skip":1},
{"data": "/6r/"},
{"skip":19},
{"data": "/4iI//8="},
{"skip":6},
{"data": "/6p//w=="},
{"skip":22},
{"data": "//+qf/8="},
{"skip":20},
{"data": "/4iI//8="},
{"skip":6},
{"data": "/6p//w=="},
{"skip":22},
{"data": "/39//w=="},
{"skip":1},
{"data": "/39//w=="},
{"skip":23},
{"data": "/4iI/w=="},
{"skip":2},
{"data": "/39//w=="},
{"skip":21},
{"data": "/39//w=="},
{"skip":2},
{"data": "/4iI/w=="},
{"skip":27},
{"data": "/3//"},
{"skip":25},
{"data": "/6r/"},
{"skip":1},
{"data": "/6qq/w=="},
{"skip":22},
{"data": "/3+q/w=="},
{"skip":6},
{"data": "//+IiP8="},
{"skip":22},
{"data": "/3+q//8="},
{"skip":24},
{"data": "/39//w=="},
{"skip":3},
{"data": "////"},
{"skip":23},
{"data": "/4iIiP+qqv8="},
{"skip":24},
{"data": "/6qq/w=="},
{"skip":3},
{"data": "/4iIiP8="},
{"skip":16},
{"data": "/4iIiIj/"},
{"skip":6},
{"data": "/6p//w=="},
{"skip":19},
{"data": "/6qq/w=="},
{"skip":4},
{"data": "/4j///8="},
{"skip":22},
{"data": "/6r//////w=="},
{"skip":20},
{"data": "/4iI/w=="},
{"skip":7},
{"data": "/3//"},
{"skip":23},
{"data": "//+qf/8="},
{"skip":20},
{"data": "/4iI/w=="},
{"skip":7},
{"data": "/6p//w=="},
{"skip":21},
{"data": "/39//w=="},
{"skip":1},
{"data": "/39//w=="},
{"skip":24},
{"data": "////"},
{"skip":2},
{"data": "/39//w=="},
{"skip":21},
{"data": "/39//w=="},
{"skip":2},
{"data": "////"},
{"skip":28},
{"data": "/3+q/w=="},
{"skip":24},
{"data": "//////+q/w=="},
{"skip":23},
{"data": "/3//"},
{"skip":7},
{"data": "/4iI/w=="},
{"skip":22},
{"data": "/3+q//8="},
{"skip":25},
{"data": "/3+q/w=="},
{"skip":29},
{"data": "//////////8="},
{"skip":24},
{"data": "//+q/w=="},
{"skip":3},
{"data": "/////w=="},
{"skip":17},
{"data": "//////8="},
{"skip":8},
{"data": "//+I/w=="},
{"skip":18},
{"data": "/6r/"},
{"skip":5},
{"data": "//+IiP8="},
{"skip":20},
{"data": "////qv//iIj/"},
{"skip":21},
{"data": "////"},
{"skip":6},
{"data": "//+qf/8="},
{"skip":24},
{"data": "/3//"},
{"skip":21},
{"data": "////"},
{"skip":7},
{"data": "/6p//w=="},
{"skip":21},
{"data": "/6p//w=="},
{"skip":1},
{"data": "/3+q/w=="},
{"skip":28},
{"data": "//9/qv8="},
{"skip":21},
{"data": "/6p///8="},
{"skip":32},
{"data": "/3+q/w=="},
{"skip":24},
{"data": "/4iI//+q////"},
{"skip":20},
{"data": "/3+q//8="},
{"skip":6},
{"data": "////"},
{"skip":23},
{"data": "/3//"},
{"skip":27},
{"data": "/3//"},
{"skip":33},
{"data": "//+IiP8="},
{"skip":22},
{"data": "//+IiP8="},
{"skip":37},
{"data": "//+IiP8="},
{"skip":16},
{"data": "//+I//8="},
{"skip":7},
{"data": "////"},
{"skip":20},
{"data": "/4j///8="},
{"skip":1},
{"data": "////"},
{"skip":30},
{"data": "/4j///8="},
{"skip":23},
{"data": "////iP8="},
{"skip":30},
{"data": "/////w=="},
{"skip":21},
{"data": "/////w=="},
{"skip":1},
{"data": "/////w=="},
{"skip":28},
{"data": "//////8="},
{"skip":21},
{"data": "//////8="},
{"skip":32},
{"data": "/////w=="},
{"skip":24},
{"data": "////"},
{"skip":1},
{"data": "////iP8="},
{"skip":20},
{"data": "////iP8="},
{"skip":31},
{"data": "/4j///8="},
{"skip":25},
{"data": "/4j///8="},
{"skip":31},
{"data": "/4iIiIj/"},
{"skip":21},
{"data": "/4iIiIj/"},
{"skip":36},
{"data": "/4iIiP8="},
{"skip":16},
{"data": "/4iIiIj/"},
{"skip":31},
{"data": "/4iI/w=="},
{"skip":35},
{"data": "/4iI/w=="},
{"skip":22},
{"data": "/4iIiIj/"},
{"skip":30},
{"data": "/4iI/w=="},
{"skip":21},
{"data": "/4iI/w=="},
{"skip":1},
{"data": "/4iI/w=="},
{"skip":28},
{"data": "//+IiP8="},
{"skip":21},
{"data": "/4iIiP8="},
{"skip":32},
{"data": "/4iI/w=="},
{"skip":28},
{"data": "/4iI/w=="},
{"skip":21},
{"data": "/4iI/w=="},
{"skip":32},
{"data": "/4iIiIj/"},
{"skip":24},
{"data": "/4iIiIj/"},
{"skip":30},
{"data": "////////"},
{"skip":21},
{"data": "////////"},
{"skip":36},
{"data": "/////w=="},
{"skip":17},
{"data": "////////"},
{"skip":32},
{"data": "////"},
{"skip":36},
{"data": "////"},
{"skip":23},
{"data": "/////w=="},
{"skip":31},
{"data": "////"},
{"skip":23},
{"data": "////"},
{"skip":1},
{"data": "////"},
{"skip":30},
{"data": "/////w=="},
{"skip":21},
{"data": "/////w=="},
{"skip":33},
{"data": "////"},
{"skip":29},
{"data": "////"},
{"skip":22},
{"data": "////"},
{"skip":34},
{"data": "/////w=="},
{"skip":25},
{"data": "//////8="},
{"skip":55},
{"data": "//8="},
{"skip":4},
{"data": "/w=="},
{"skip":1},
{"data": "//8="},
{"skip":95},
{"data": "/////w=="},
{"skip":25},
{"data": "/////w=="},
{"skip":29},
{"data": "//////8="},
{"skip":27},
{"data": "//////8="},
{"skip":91},
{"data": "//////8="},
{"skip":27},
{"data": "//////8="},
{"skip":59},
{"data": "//////8="},
{"skip":115},
{"data": "/w8I/w=="},
{"skip":2},
{"data": "/4H/gaz/"},
{"skip":8},
{"data": "//8="},
{"skip":82},
{"data": "//+BgYGs/w=="},
{"skip":23},
{"data": "/6yBgYH//w=="},
{"skip":26},
{"data": "/6yBgYGs/w=="},
{"skip":25},
{"data": "/6yBgYGs/w=="},
{"skip":89},
{"data": "/6yBgYGs/w=="},
{"skip":25},
{"data": "/6yBgYGs/w=="},
{"skip":57},
{"data": "/6ysgYGB//8="},
{"skip":58},
{"data": "////////"},
{"skip":49},
{"data": "/w8I/w=="},
{"skip":1},
{"data": "/4GBrIGBrP8="},
{"skip":6},
{"data": "/zkI/w=="},
{"skip":81},
{"data": "/6ysrIGBrP8="},
{"skip":21},
{"data": "/6yBgaysrP8="},
{"skip":26},
{"data": "/4Gsgf+B/w=="},
{"skip":25},
{"data": "/6yBgYGs/w=="},
{"skip":89},
{"data": "/4Gsgf+B/w=="},
{"skip":16},
{"data": "//8="},
{"skip":7},
{"data": "/4Gsgf+B/w=="},
{"skip":57},
{"data": "/6yBgaysrP8="},
{"skip":56},
{"data": "//+srIGBgaz/"},
{"skip":47},
{"data": "/8P//w=="},
{"skip":1},
{"data": "/6yBrP//rIGs/w=="},
{"skip":4},
{"data": "//8P/w=="},
{"skip":50},
{"data": "//////8="},
{"skip":28},
{"data": "////gf+B/w=="},
{"skip":21},
{"data": "/4H/gf///w=="},
{"skip":26},
{"data": "/6ysgf8P/6z/"},
{"skip":23},
{"data": "/4GsgYH/gf8="},
{"skip":88},
{"data": "/6ysgf8P/6z/"},
{"skip":14},
{"data": "/w85/w=="},
{"skip":5},
{"data": "/6ysgf8P/6z/"},
{"skip":56},
{"data": "/6z/gf///w=="},
{"skip":56},
{"data": "/4GsrIGBrP+BrP8="},
{"skip":46},
{"data": "/8PK/w=="},
{"skip":1},
{"data": "/6yB/w8P/6z/"},
{"skip":3},
{"data": "///Dw/8="},
{"skip":50},
{"data": "/6yBgYGs/w=="},
{"skip":27},
{"data": "/zk5/w//rP8="},
{"skip":19},
{"data": "/6z/D/85Of8="},
{"skip":26},
{"data": "/4H//wg5/4H/"},
{"skip":23},
{"data": "/6yBrP85/6z/"},
{"skip":87},
{"data": "/4H//wg5/4H/"},
{"skip":14},
{"data": "/zkI/w=="},
{"skip":5},
{"data": "/4H//wg5/4H/"},
{"skip":55},
{"data": "/4H/D/85Of8="},
{"skip":24},
{"data": "/////w=="},
{"skip":29},
{"data": "/6ysrP//D/+B/w=="},
{"skip":45},
{"data": "/8PK/w=="},
{"skip":2},
{"data": "/4H/OQg5/4Gs////w8PD/w=="},
{"skip":51},
{"data": "/4Gsgf+B/w=="},
{"skip":27},
{"data": "/wgID/+sgf8="},
{"skip":19},
{"data": "/4Gs/w8ICP8="},
{"skip":26},
{"data": "/4H/DwgP/4H/"},
{"skip":23},
{"data": "/////w8P/4H/"},
{"skip":25},
{"data": "//////8="},
{"skip":57},
{"data": "/4H/DwgP/4H/"},
{"skip":15},
{"data": "/zn/"},
{"skip":5},
{"data": "/6z/DwgP/4H/"},
{"skip":25},
{"data": "//////8="},
{"skip":25},
{"data": "/4Gs/w8ICP///w=="},
{"skip":21},
{"data": "/6yBgaz/"},
{"skip":28},
{"data": "/4Gs/zkIOf//"},
{"skip":46},
{"data": "/8PK/w=="},
{"skip":2},
{"data": "/6z/DwgP/6z//7bDw8r/"},
{"skip":51},
{"data": "/6ysgf8P/6z/"},
{"skip":24},
{"data": "////OQ///6z//w=="},
{"skip":19},
{"data": "//+s//8POf//"},
{"skip":23},
{"data": "////rP85Dzn/rP///w=="},
{"skip":21},
{"data": "/6z/OQg5/6z/"},
{"skip":24},
{"data": "/6yBgYGs/w=="},
{"skip":54},
{"data": "////rP85Dzn/rP///w=="},
{"skip":14},
{"data": "/7b/"},
{"skip":2},
{"data": "//////85Dzn/rP///w=="},
{"skip":22},
{"data": "/6yBgYGs/w=="},
{"skip":24},
{"data": "//+s//8POf+2tv8="},
{"skip":20},
{"data": "/4GBrIGB//8="},
{"skip":27},
{"data": "/4H/DwgP/6z/"},
{"skip":45},
{"data": "/8rK////////OQ85//+2tsPD//8="},
{"skip":22},
{"data": "//////8="},
{"skip":25},
{"data": "/4H//wg5/4H/"},
{"skip":23},
{"data": "/1kv/w//Of//trb/"},
{"skip":17},
{"data": "/7bD//85/w//tv//"},
{"skip":20},
{"data": "/7a2Wf///wj///+2trb/"},
{"skip":18},
{"data": "//9Z////Of///7b//w=="},
{"skip":22},
{"data": "/4Gsgf+B/w=="},
{"skip":53},
{"data": "/7a2Wf///wj///+2trb/"},
{"skip":12},
{"data": "/8PD/w=="},
{"skip":1},
{"data": "/7a2WVn//wj///+2trb/"},
{"skip":20},
{"data": "/6yBgYGBrP8="},
{"skip":23},
{"data": "/1kv/zn//w//tsP/"},
{"skip":19},
{"data": "/4Gsgaz/rIGs/w=="},
{"skip":24},
{"data": "////rP85Dzn/gf8="},
{"skip":45},
{"data": "/8rKw7a2Wf///wj//8O2w8P/"},
{"skip":23},
{"data": "/6yBgYGs/w=="},
{"skip":24},
{"data": "/4H/DwgP/4H/"},
{"skip":22},
{"data": "/7ZZWS//OTn/tsPD/w=="},
{"skip":17},
{"data": "/8PDL/85Of+2tra2/w=="},
{"skip":19},
{"data": "/8O2WS//Of85/7a2tsP/"},
{"skip":17},
{"data": "/7a2WS//Of85/7a2trb/"},
{"skip":20},
{"data": "/6ysgf8P/6z/"},
{"skip":52},
{"data": "/8O2WS//Of85/7a2tsP/"},
{"skip":13},
{"data": "/8PD/8PDw1kv/zn/Of+2trbD/w=="},
{"skip":19},
{"data": "/4GsrIGB/4Gs/w=="},
{"skip":21},
{"data": "/7a2WS//CA//w8PD/w=="},
{"skip":19},
{"data": "//+srP8P/6z//w=="},
{"skip":23},
{"data": "/7a2Wf//Of//rP8="},
{"skip":47},
{"data": "///Kw8PKL/85/zn/w8PD/w=="},
{"skip":24},
{"data": "/4Gsgf+B/w=="},
{"skip":23},
{"data": "/4Gs/zkPOf+s/w=="},
{"skip":21},
{"data": "/7a2ylkvw/8P/8PDw8P/"},
{"skip":15},
{"data": "/8PDwy//D//Dw8O2trb/"},
{"skip":18},
{"data": "/8PDylkv/w//w8PDw8P/"},
{"skip":17},
{"data": "/8O2w1kv/w//w8PDtsP/"},
{"skip":20},
{"data": "/4H//wg5/4H/"},
{"skip":51},
{"data": "/7bKw8pZL/8P/8PDw8PKtv8="},
{"skip":12},
{"data": "/8PDw8PKyspZL/8P/8PDw8PD/w=="},
{"skip":18},
{"data": "/////4Gs/zn/rP///w=="},
{"skip":19},
{"data": "/8O2tlkv/zn/w//K/w=="},
{"skip":19},
{"data": "/w///wj///+2tv8="},
{"skip":16},
{"data": "/w=="},
{"skip":5},
{"data": "/8q2WS//OTn/gf///w=="},
{"skip":47},
{"data": "////ylkv/w//w8PD/w=="},
{"skip":24},
{"data": "/6ysgf8P/6z/"},
{"skip":22},
{"data": "/6ys//8I////w///"},
{"skip":19},
{"data": "/8PKyspZL8P/w8PD/8P/"},
{"skip":15},
{"data": "/8P/w1kv/8PDw8PDysP/"},
{"skip":18},
{"data": "/8P/w8pZL//Dw8PD/8P/"},
{"skip":16},
{"data": "/8PDw8PKWS//w8PDw8PDw/8="},
{"skip":19},
{"data": "/4H/DwgP/4H/"},
{"skip":51},
{"data": "/8PK/8PKWS//w8PDw//Kw/8="},
{"skip":13},
{"data": "/8PKyv//w8pZL//Dw8PK/8P/"},
{"skip":17},
{"data": "/7bDWVn//w8P//+2trb/"},
{"skip":18},
{"data": "/8rDtv9Z////w//K/w=="},
{"skip":20},
{"data": "/zn/OQ///8O2tv8="},
{"skip":14},
{"data": "/w//"},
{"skip":3},
{"data": "/8rKw1kv/w//w/+2trb/"},
{"skip":49},
{"data": "/8ovw//Dw8PK/w=="},
{"skip":24},
{"data": "/4H//wg5/4H/"},
{"skip":21},
{"data": "/1n///85/zn/tra2tv8="},
{"skip":18},
{"data": "/8PK/8PKWS/Dw8PK/8PD/w=="},
{"skip":13},
{"data": "/8PD/8rKL8PDw8PD/8rD/w=="},
{"skip":19},
{"data": "///Kw8pZL8PDw8r//w=="},
{"skip":17},
{"data": "/8PD/8rDylkvw8PDyv/Dw/8="},
{"skip":19},
{"data": "/6z/OQ85/6z///8="},
{"skip":48},
{"data": "/8PK/w=="},
{"skip":1},
{"data": "/8PKWS/Dw8P/"},
{"skip":1},
{"data": "/8rD/w=="},
{"skip":13},
{"data": "////"},
{"skip":2},
{"data": "/8PKWS/Dw8PK/8P/"},
{"skip":17},
{"data": "/7bDWS//OQg5/8O2trb/"},
{"skip":19},
{"data": "/8rDtv/Dyv/D/8r/"},
{"skip":20},
{"data": "////////w/+2tv8="},
{"skip":14},
{"data": "/zkI/////8rK/7ZZL/+2w7bDtsP/"},
{"skip":12},
{"data": "/////w=="},
{"skip":2},
{"data": "////"},
{"skip":28},
{"data": "/8pZL8PDw8P/"},
{"skip":25},
{"data": "/4H/DwgP/4Gs/w=="},
{"skip":19},
{"data": "/7a2WS/D/w//w7a2w8P/"},
{"skip":17},
{"data": "/7bDyv/Kw8pZL8PD/8rDyv8="},
{"skip":13},
{"data": "/8rDw//KWS/Dw8PK/8rDtv8="},
{"skip":18},
{"data": "/8P/w8PKWS/Dw//D/w=="},
{"skip":16},
{"data": "/8PDw///w8PKWS/Dw///w8PD/w=="},
{"skip":17},
{"data": "/1n///8I////tra2/w=="},
{"skip":29},
{"data": "/////w=="},
{"skip":14},
{"data": "/8rKyv//w8PKWS/Dw///ysrK/w=="},
{"skip":18},
{"data": "/8PDylkvw8P//8PD/w=="},
{"skip":16},
{"data": "/8PDyi///zn//8O2w8PD/w=="},
{"skip":18},
{"data": "/8rDw//Dyv/D/8P/"},
{"skip":19},
{"data": "/7b/w//Ktv+2w8P/"},
{"skip":15},
{"data": "/zn/trbDyv//tsMvtsO2w//Kyv8="},
{"skip":11},
{"data": "/4GB/6z//8PDw///////"},
{"skip":23},
{"data": "/8PKWS/Dw8r/"},
{"skip":25},
{"data": "/6z/OQ85/6z/rP8="},
{"skip":18},
{"data": "/8PDylkvw//Dw8PKw8P/"},
{"skip":17},
{"data": "/7bD/w=="},
{"skip":1},
{"data": "/8PDylkvyv/Kyv8="},
{"skip":15},
{"data": "/8rK/8PKWS/Dw/8="},
{"skip":1},
{"data": "/8O2/w=="},
{"skip":18},
{"data": "/8P/ysPDylkvyv/D/w=="},
{"skip":16},
{"data": "/7bD/w=="},
{"skip":1},
{"data": "/8rDw8pZL8P/"},
{"skip":1},
{"data": "/8O2/w=="},
{"skip":16},
{"data": "/7ZZL/85/zn/tra2w/8="},
{"skip":26},
{"data": "////w7a2w/////8="},
{"skip":11},
{"data": "/8PD///Kw8PKWS/K///Dw/8="},
{"skip":19},
{"data": "/8rDw8pZL8r//8PD/w=="},
{"skip":15},
{"data": "/8PDw8rKL////8rDw//Kw/8="},
{"skip":19},
{"data": "/8rDw8r/L/+2w/8="},
{"skip":19},
{"data": "/8PK///Kw//Dw8r/"},
{"skip":16},
{"data": "////w8P/"},
{"skip":1},
{"data": "/8O2WS/Dw8r/ysrK/w=="},
{"skip":9},
{"data": "/4GB/zn//zn/w8P//8PD/w=="},
{"skip":23},
{"data": "/8rDylkvysr/"},
{"skip":23},
{"data": "//9Z////CP///8P//w=="},
{"skip":18},
{"data": "/8PD/8pZL8PDw8P/w8P/"},
{"skip":17},
{"data": "/8O2/w=="},
{"skip":1},
{"data": "/8rDyspZL//K/w=="},
{"skip":17},
{"data": "/8r/ysPKWS/D/w=="},
{"skip":1},
{"data": "/7bD/w=="},
{"skip":19},
{"data": "///DysPKylkv//8="},
{"skip":15},
{"data": "//+2w8r/"},
{"skip":1},
{"data": "/8PKw8PKWS//"},
{"skip":1},
{"data": "/8rDtv//"},
{"skip":13},
{"data": "/7a2tlkv/w//w8PDw8P/"},
{"skip":23},
{"data": "////w8PDw7a2tv+sgYH//w=="},
{"skip":10},
{"data": "/8PD/8rKw8rKWS//w8P/"},
{"skip":20},
{"data": "/8PKw8rKWS///8PK/w=="},
{"skip":15},
{"data": "/8PD/8rKWVnKysrKyv//w/8="},
{"skip":19},
{"data": "///Kw8r//7bDyv8="},
{"skip":19},
{"data": "/8rK///Kw8PK/8r/"},
{"skip":19},
{"data": "//8="},
{"skip":2},
{"data": "/8q2wy/Dw8r//8rKtv//"},
{"skip":2},
{"data": "/w=="},
{"skip":4},
{"data": "/4H/OQg5//8vL/8POf////////8="},
{"skip":20},
{"data": "/8rDylkvyv8="},
{"skip":22},
{"data": "/7bDL8P/Of85/7a2trb/"},
{"skip":17},
{"data": "/8PD/8PKWS/Dw8P/w8P/"},
{"skip":17},
{"data": "/8O2yv//w8rDyspZ//8="},
{"skip":19},
{"data": "///KysPKWS///8q2w/8="},
{"skip":19},
{"data": "///Kw8rDyspZ//8="},
{"skip":14},
{"data": "/wj/w///"},
{"skip":2},
{"data": "/8rDysrDyln/"},
{"skip":2},
{"data": "///D/wj/"},
{"skip":12},
{"data": "/8PDw8pZL//Dw8PD/8PD/w=="},
{"skip":19},
{"data": "////ysrDw8PKw7a2w/////+BrP8="},
{"skip":10},
{"data": "//85/8rKw8rK/zn//w=="},
{"skip":21},
{"data": "/8rDysPKyln//8PK/w=="},
{"skip":15},
{"data": "/8PK///KyllZysrK/8rKyv8="},
{"skip":19},
{"data": "/8r///8P/8P//w=="},
{"skip":21},
{"data": "//8="},
{"skip":1},
{"data": "/8rDyv/Kyv8="},
{"skip":23},
{"data": "/8rDw1kvysr/"},
{"skip":1},
{"data": "/8PDw7b//w//"},
{"skip":2},
{"data": "/6ys/zkP/1lZWVn/CA//yv9ZysrC//////8="},
{"skip":15},
{"data": "/8rKw8pZL/8="},
{"skip":22},
{"data": "/8O2WS/D/w//w8PDtsP/"},
{"skip":17},
{"data": "/8PD/8rDylkvw8P/w8P/"},
{"skip":18},
{"data": "/8P//8rKysrKLy//"},
{"skip":21},
{"data": "/y8vysrKWVn//8P/"},
{"skip":21},
{"data": "/y/KysrKyi//"},
{"skip":14},
{"data": "/w85//8="},
{"skip":4},
{"data": "/y/KysrKyi//"},
{"skip":4},
{"data": "//85D/8="},
{"skip":11},
{"data": "/8PD/8PKWS/Dw8PK/8rD/w=="},
{"skip":17},
{"data": "///KWS/KysrKysrDtsP/Of8POf+B/w=="},
{"skip":12},
{"data": "/w//ysrK/w//"},
{"skip":23},
{"data": "/y/KysrKyi///8PK/w=="},
{"skip":14},
{"data": "/7bD/w=="},
{"skip":1},
{"data": "/8PKyllZysr/yv//"},
{"skip":20},
{"data": "/y/K/zkP////"},
{"skip":25},
{"data": "/////1nKyv8="},
{"skip":23},
{"data": "/y/Kw8pZyv8="},
{"skip":3},
{"data": "///Kw/8IOf8="},
{"skip":2},
{"data": "/4GsrP//ysrKyspH///KylnKw8P/qn9/f3//"},
{"skip":14},
{"data": "/y/KysrKWf8="},
{"skip":22},
{"data": "/8PDylkvw//Dw8PDw8P/"},
{"skip":17},
{"data": "/8PDyv/Kw8pZL8r/w8P/"},
{"skip":19},
{"data": "/zkP/y8vLy9ZWf8="},
{"skip":21},
{"data": "/1lZLy8vL/8POf8="},
{"skip":22},
{"data": "/1kvLy8vL1n/"},
{"skip":15},
{"data": "//8="},
{"skip":6},
{"data": "/1kvLy8vL1n/"},
{"skip":6},
{"data": "//8="},
{"skip":12},
{"data": "/8PD/8PDylkvw8P//8rK/w=="},
{"skip":16},
{"data": "/8PDw8pZL8rKysr/w7bD//8IOQj/gaz/"},
{"skip":11},
{"data": "//8vLy8vL///"},
{"skip":23},
{"data": "/1kvLy8vL1n/"},
{"skip":1},
{"data": "////"},
{"skip":14},
{"data": "/7bD/w=="},
{"skip":1},
{"data": "/y/KyspZWVn//w=="},
{"skip":22},
{"data": "/1kvL////1n/"},
{"skip":25},
{"data": "/1nKWS8vWf8="},
{"skip":23},
{"data": "/1kvyspZL/8="},
{"skip":5},
{"data": "////Of8="},
{"skip":4},
{"data": "/4Gs/8rDw8PDw0dHysovysrKw/+qqqr/f/8="},
{"skip":13},
{"data": "//9ZLy8vLy//"},
{"skip":22},
{"data": "/8PD/8pZL8PDw8P/w8P/"},
{"skip":18},
{"data": "/8PD/8rKyspZL/+2/w=="},
{"skip":21},
{"data": "/wj/WVlZWcrK/w=="},
{"skip":21},
{"data": "/8rKWVlZWf8I/w=="},
{"skip":23},
{"data": "/8pZWVlZWcr/"},
{"skip":23},
{"data": "/8pZWVlZWcr/"},
{"skip":20},
{"data": "/8PD/8rDw8pZL8r//8rK/w=="},
{"skip":16},
{"data": "////w8PKWS/Kysr/tsP/yv//////rIH/"},
{"skip":11},
{"data": "/8pZWVlZWcr/"},
{"skip":23},
{"data": "/8pZWVlZWcr//wg5/w=="},
{"skip":12},
{"data": "//+2w/8="},
{"skip":2},
{"data": "/1kvLy8vL1n/"},
{"skip":23},
{"data": "/8pZWVlZWcr/"},
{"skip":25},
{"data": "/8pZL1lZWf8="},
{"skip":23},
{"data": "/8pZWcpZL/8="},
{"skip":8},
{"data": "/w=="},
{"skip":6},
{"data": "////w8PDysrKR8rKL1n/w8rK/6r//6qq/2uP"},
{"skip":1},
{"data": "jw=="},
{"skip":9},
{"data": "/8PKWVlZWVnK/w=="},
{"skip":21},
{"data": "/8PD/8PKWS/Dw8P/w8P/"},
{"skip":18},
{"data": "/8O2/y8vLy8v/7bD/w=="},
{"skip":22},
{"data": "/8rKysrKysr/"},
{"skip":21},
{"data": "/8rKysrKysr/"},
{"skip":24},
{"data": "/8PKysrKysP/"},
{"skip":22},
{"data": "/8rDysrKysrK/w=="},
{"skip":20},
{"data": "/8PD/8rKw8rKWS//ysr/"},
{"skip":16},
{"data": "/39/f//Kysr//////7bD//8POf/Dyv//"},
{"skip":12},
{"data": "/8PKysrKysP/"},
{"skip":22},
{"data": "/8rDysrKysrD//85D/8="},
{"skip":11},
{"data": "/wj/tv8="},
{"skip":3},
{"data": "/8pZWVlZWcr/"},
{"skip":22},
{"data": "/8rDysrKysrK/w=="},
{"skip":24},
{"data": "/8PKylnKysr/"},
{"skip":22},
{"data": "/8rDyspZWVn/"},
{"skip":14},
{"data": "j4+P////yv///0f//1nK/8PKyv//j/+qqv9Ha48j"},
{"skip":9},
{"data": "/8rDysrKysrD/w=="},
{"skip":21},
{"data": "/8PD/8rDylkvw8P/w8P/"},
{"skip":19},
{"data": "/8O2/1lZWVn/////"},
{"skip":22},
{"data": "/8PKysrKyv//"},
{"skip":21},
{"data": "///KysrKysP/"},
{"skip":24},
{"data": "/8PDysrKw8P/"},
{"skip":22},
{"data": "/8PDysrKysPD/w=="},
{"skip":20},
{"data": "/8O2w//KysPKyln/ysr/"},
{"skip":16},
{"data": "/39/qv////+q/w=="},
{"skip":2},
{"data": "/8PKysr//8q2w/8="},
{"skip":12},
{"data": "/8PDysrKysrD/w=="},
{"skip":22},
{"data": "/8PDw8rKysPD/w=="},
{"skip":1},
{"data": "//8="},
{"skip":12},
{"data": "/zkP/w=="},
{"skip":4},
{"data": "/8PKysrKysP/"},
{"skip":22},
{"data": "/8PDw8rKysrD/w=="},
{"skip":24},
{"data": "/8PKw8PDysr/"},
{"skip":22},
{"data": "/8PDw8rKysr/"},
{"skip":12},
{"data": "j4+Pj/8ICA//j4+Pa2uP//9//8P/qv+Pj/+q/2uP"},
{"skip":1},
{"data": "jw=="},
{"skip":9},
{"data": "///Dw8rKysPDtv8="},
{"skip":20},
{"data": "/8PDyv/Kw8pZL//Kw8P/"},
{"skip":19},
{"data": "/////8rKysr/Dwj/"},
{"skip":22},
{"data": "/8PDw8rD/6r/"},
{"skip":21},
{"data": "/6r/w8rDw8P/"},
{"skip":24},
{"data": "/8rDysrKw8r/"},
{"skip":23},
{"data": "///DysrKw///"},
{"skip":21},
{"data": "/8O2///KysrKL//K/w=="},
{"skip":15},
{"data": "//9/f6r/qqr/qqp//w=="},
{"skip":2},
{"data": "////////////"},
{"skip":13},
{"data": "///Kw8rKysP//w=="},
{"skip":23},
{"data": "/8rDysrKw8r/"},
{"skip":16},
{"data": "//8="},
{"skip":5},
{"data": "/8rDysrKw8r/"},
{"skip":23},
{"data": "/8rDysrKw///"},
{"skip":24},
{"data": "////w8P///8="},
{"skip":23},
{"data": "////w8rDw8rK/w=="},
{"skip":12},
{"data": "j4+P//8P//+Pa2tr"},
{"skip":1},
{"data": "a4//qv//qn+q/4////+P"},
{"skip":1},
{"data": "jw=="},
{"skip":10},
{"data": "/6r//8PKw7b///8="},
{"skip":20},
{"data": "/8rDtv/KysrKWf+2w8r/"},
{"skip":18},
{"data": "/zP/Dwj///////85//8="},
{"skip":20},
{"data": "/3///////6qq/w=="},
{"skip":21},
{"data": "/6qq//////9//w=="},
{"skip":23},
{"data": "////ysrD////"},
{"skip":23},
{"data": "/6r////K/6r/"},
{"skip":21},
{"data": "////Dwj/Ly8vWf///w=="},
{"skip":13},
{"data": "//+qqn+q////qqr/f3//"},
{"skip":24},
{"data": "/6r///////+q/w=="},
{"skip":23},
{"data": "////ysrD////"},
{"skip":23},
{"data": "////ysrD////"},
{"skip":23},
{"data": "/////////6r/"},
{"skip":23},
{"data": "/39/qv//qqr/"},
{"skip":23},
{"data": "/39/////yv///w=="},
{"skip":14},
{"data": "/8PD/7P/aw=="},
{"skip":1},
{"data": "jw=="},
{"skip":1},
{"data": "a4+P/////6p/f/+P/4iI/48="},
{"skip":11},
{"data": "/39///////+qf3//"},
{"skip":20},
{"data": "///Dtv8vLy//tsP//w=="},
{"skip":19},
{"data": "/zP//zn//6qqqv//M/8="},
{"skip":20},
{"data": "/3+qqv8="},
{"skip":1},
{"data": "/6qq/w=="},
{"skip":21},
{"data": "/6qq/w=="},
{"skip":1},
{"data": "/6qqf/8="},
{"skip":23},
{"data": "/6qq////qqr/"},
{"skip":23},
{"data": "/3+q/w=="},
{"skip":1},
{"data": "/6p//w=="},
{"skip":21},
{"data": "/8P//zn/WVlZyv85/w=="},
{"skip":12},
{"data": "/6qqqqqq/4j/"},
{"skip":1},
{"data": "//+q/3//"},
{"skip":24},
{"data": "/6qqqv8="},
{"skip":1},
{"data": "/6qq/w=="},
{"skip":23},
{"data": "/6qq////qqr/"},
{"skip":23},
{"data": "/6qq////qqr/"},
{"skip":23},
{"data": "/6qq/w=="},
{"skip":1},
{"data": "/39//w=="},
{"skip":23},
{"data": "/39///9/f/8="},
{"skip":23},
{"data": "/39/qv8="},
{"skip":2},
{"data": "/6qq/w=="},
{"skip":14},
{"data": "/8PK/2tra4+Pj2uP/8PKyv//qn9/////iIj/"},
{"skip":11},
{"data": "/39//w=="},
{"skip":4},
{"data": "/39//w=="},
{"skip":19},
{"data": "/8PD//8P/1n/D///w8P/"},
{"skip":18},
{"data": "/4n/f/+q////f3//if8="},
{"skip":20},
{"data": "/3+q/w=="},
{"skip":2},
{"data": "/6r/"},
{"skip":23},
{"data": "/6r/"},
{"skip":2},
{"data": "/6p//w=="},
{"skip":23},
{"data": "/39//w=="},
{"skip":1},
{"data": "/39//w=="},
{"skip":23},
{"data": "/39//w=="},
{"skip":1},
{"data": "/39//w=="},
{"skip":22},
{"data": "/39//8PKysrK////"},
{"skip":11},
{"data": "/6qqqv///w=="},
{"skip":1},
{"data": "/w=="},
{"skip":4},
{"data": "////"},
{"skip":25},
{"data": "/3+q/w=="},
{"skip":2},
{"data": "/6qqf/8="},
{"skip":22},
{"data": "/39//w=="},
{"skip":1},
{"data": "/39//w=="},
{"skip":23},
{"data": "/39//w=="},
{"skip":1},
{"data": "/39//w=="},
{"skip":23},
{"data": "/39//w=="},
{"skip":1},
{"data": "/39//w=="},
{"skip":23},
{"data": "/6qq//9/f/8="},
{"skip":23},
{"data": "/3+qqv8="},
{"skip":3},
{"data": "/6qq/w=="},
{"skip":12},
{"data": "/8PD/2s="},
{"skip":3},
{"data": "jw=="},
{"skip":1},
{"data": "jw=="},
{"skip":1},
{"data": "a2v///+Pj/+qf6r/"},
{"skip":1},
{"data": "////"},
{"skip":11},
{"data": "/3+q/w=="},
{"skip":4},
{"data": "/6qqqv8="},
{"skip":18},
{"data": "////yv8IOf85CP/K////"},
{"skip":19},
{"data": "//9/f6r//6qqqv//"},
{"skip":20},
{"data": "/3+q/w=="},
{"skip":2},
{"data": "/6qq/w=="},
{"skip":23},
{"data": "/6qq/w=="},
{"skip":2},
{"data": "/6p//w=="},
{"skip":22},
{"data": "/39//w=="},
{"skip":1},
{"data": "/39//w=="},
{"skip":23},
{"data": "/3+q/w=="},
{"skip":1},
{"data": "/39//w=="},
{"skip":22},
{"data": "/39//8rDysrK/w=="},
{"skip":12},
{"data": "/4j///8="},
{"skip":37},
{"data": "/3+q/w=="},
{"skip":3},
{"data": "/39//w=="},
{"skip":22},
{"data": "/39//w=="},
{"skip":1},
{"data": "/39//w=="},
{"skip":23},
{"data": "/39//w=="},
{"skip":1},
{"data": "/39//w=="},
{"skip":23},
{"data": "/39//w=="},
{"skip":1},
{"data": "/6p//w=="},
{"skip":24},
{"data": "/6qq/6qq/w=="},
{"skip":23},
{"data": "/6qq/w=="},
{"skip":4},
{"data": "/3+q/w=="},
{"skip":12},
{"data": "/////w=="},
{"skip":7},
{"data": "jw=="},
{"skip":1},
{"data": "jw=="},
{"skip":1},
{"data": "j4+Pj4//qn//j48="},
{"skip":13},
{"data": "/6qq/w=="},
{"skip":5},
{"data": "/6qq/w=="},
{"skip":18},
{"data": "/39///////////9/f3//"},
{"skip":20},
{"data": "/6qqqv+qqqr//w=="},
{"skip":21},
{"data": "/3+q/w=="},
{"skip":2},
{"data": "/6qq/w=="},
{"skip":23},
{"data": "/6qq/w=="},
{"skip":2},
{"data": "/6p//w=="},
{"skip":22},
{"data": "/6p//w=="},
{"skip":1},
{"data": "/3+q/w=="},
{"skip":23},
{"data": "/6qq/w=="},
{"skip":1},
{"data": "/3+q/w=="},
{"skip":22},
{"data": "/3+qqv/Kw8rD/w=="},
{"skip":12},
{"data": "/4iI/w=="},
{"skip":37},
{"data": "/3+q/w=="},
{"skip":4},
{"data": "/6p//w=="},
{"skip":22},
{"data": "/6p//w=="},
{"skip":1},
{"data": "/3+q/w=="},
{"skip":23},
{"data": "/6p//w=="},
{"skip":1},
{"data": "/3+q/w=="},
{"skip":23},
{"data": "/6p//w=="},
{"skip":1},
{"data": "/6qq/w=="},
{"skip":24},
{"data": "/6qq//+qqv8="},
{"skip":22},
{"data": "/6qq/w=="},
{"skip":3},
{"data": "/3+q/w=="},
{"skip":13},
{"data": "/zkP/w=="},
{"skip":10},
{"data": "jw=="},
{"skip":1},
{"data": "jw=="},
{"skip":1},
{"data": "jw=="},
{"skip":1},
{"data": "/6p/f/+Pj///"},
{"skip":11},
{"data": "/6qq/w=="},
{"skip":4},
{"data": "/6qq/w=="},
{"skip":18},
{"data": "/39/f3+qqv+qqqqqf3//"},
{"skip":20},
{"data": "//+qqv//qv+J/w=="},
{"skip":21},
{"data": "/6qq/w=="},
{"skip":2},
{"data": "/6r//w=="},
{"skip":23},
{"data": "//+q/w=="},
{"skip":2},
{"data": "/6qq/w=="},
{"skip":22},
{"data": "/6qq/w=="},
{"skip":1},
{"data": "/6qq/w=="},
{"skip":23},
{"data": "/6qq/w=="},
{"skip":1},
{"data": "/6qq/w=="},
{"skip":23},
{"data": "/6qq////////"},
{"skip":13},
{"data": "/4j/"},
{"skip":37},
{"data": "/6qq/w=="},
{"skip":4},
{"data": "/6qq/w=="},
{"skip":22},
{"data": "/6qq/w=="},
{"skip":1},
{"data": "/6qq/w=="},
{"skip":23},
{"data": "/6qq/w=="},
{"skip":1},
{"data": "/6qq/w=="},
{"skip":23},
{"data": "/6qq/w=="},
{"skip":1},
{"data": "/6qq/w=="},
{"skip":24},
{"data": "//////+qqv8="},
{"skip":22},
{"data": "/6qq/w=="},
{"skip":3},
{"data": "//+q/w=="},
{"skip":14},
{"data": "/wj/"},
{"skip":13},
{"data": "jw=="},
{"skip":1},
{"data": "jw=="},
{"skip":1},
{"data": "/6p/f///iP8="},
{"skip":12},
{"data": "//+q/w=="},
{"skip":4},
{"data": "/6r/"},
{"skip":19},
{"data": "//+qqn9/qv//qqr//w=="},
{"skip":20},
{"data": "/zP/qqr/iP//iTP/"},
{"skip":20},
{"data": "//+q/w=="},
{"skip":2},
{"data": "//+I/w=="},
{"skip":23},
{"data": "/4j//w=="},
{"skip":2},
{"data": "/6r///8="},
{"skip":21},
{"data": "//+q/w=="},
{"skip":1},
{"data": "/6r//w=="},
{"skip":23},
{"data": "//+q/w=="},
{"skip":1},
{"data": "/6r//w=="},
{"skip":23},
{"data": "/6qq//+qqqr/"},
{"skip":14},
{"data": "//8="},
{"skip":37},
{"data": "/////w=="},
{"skip":4},
{"data": "/////w=="},
{"skip":22},
{"data": "//+q/w=="},
{"skip":1},
{"data": "/6r//w=="},
{"skip":23},
{"data": "//+q/w=="},
{"skip":1},
{"data": "/6r//w=="},
{"skip":23},
{"data": "//+q/w=="},
{"skip":1},
{"data": "/////w=="},
{"skip":23},
{"data": "/4iI////////"},
{"skip":23},
{"data": "////"},
{"skip":2},
{"data": "/4iI/w=="},
{"skip":16},
{"data": "/w=="},
{"skip":17},
{"data": "jw=="},
{"skip":1},
{"data": "//9//4iI/w=="},
{"skip":12},
{"data": "/4j//w=="},
{"skip":4},
{"data": "//+I/w=="},
{"skip":19},
{"data": "/////6qqqqr///8="},
{"skip":21},
{"data": "/4n/////iIj//4n/"},
{"skip":19},
{"data": "/4iI/w=="},
{"skip":4},
{"data": "/4iI/w=="},
{"skip":21},
{"data": "/4iI/w=="},
{"skip":4},
{"data": "/4iI/w=="},
{"skip":21},
{"data": "/4j//w=="},
{"skip":1},
{"data": "//+I/w=="},
{"skip":23},
{"data": "/4j//w=="},
{"skip":1},
{"data": "//+I/w=="},
{"skip":23},
{"data": "/////w=="},
{"skip":1},
{"data": "/6qq/w=="},
{"skip":53},
{"data": "/4iI/w=="},
{"skip":4},
{"data": "/4iI/w=="},
{"skip":22},
{"data": "/4j//w=="},
{"skip":1},
{"data": "//+I/w=="},
{"skip":23},
{"data": "/4j//w=="},
{"skip":1},
{"data": "//+I/w=="},
{"skip":23},
{"data": "/4j//w=="},
{"skip":1},
{"data": "/4iI/w=="},
{"skip":23},
{"data": "////"},
{"skip":2},
{"data": "/4iI/w=="},
{"skip":22},
{"data": "/4iI/w=="},
{"skip":2},
{"data": "/4iIiP8="},
{"skip":37},
{"data": "//+I/w=="},
{"skip":12},
{"data": "/4iI/w=="},
{"skip":5},
{"data": "/4iIiP8="},
{"skip":18},
{"data": "/4iI//////+IiP8="},
{"skip":21},
{"data": "//+IiIj///8="},
{"skip":2},
{"data": "//8="},
{"skip":18},
{"data": "/4iIiP8="},
{"skip":5},
{"data": "////"},
{"skip":21},
{"data": "////"},
{"skip":5},
{"data": "/4iIiP8="},
{"skip":20},
{"data": "/4iI/w=="},
{"skip":1},
{"data": "/4iI/w=="},
{"skip":22},
{"data": "/4iI//8="},
{"skip":1},
{"data": "/4iI/w=="},
{"skip":22},
{"data": "/4iIiP8="},
{"skip":1},
{"data": "/6qq/w=="},
{"skip":52},
{"data": "/4iI//8="},
{"skip":4},
{"data": "//+IiP8="},
{"skip":21},
{"data": "/4iI/w=="},
{"skip":1},
{"data": "/4iI/w=="},
{"skip":23},
{"data": "/4iI/w=="},
{"skip":1},
{"data": "/4iI/w=="},
{"skip":23},
{"data": "/4iI/w=="},
{"skip":1},
{"data": "//+IiP8="},
{"skip":26},
{"data": "/4iIiP8="},
{"skip":22},
{"data": "/4iI/w=="},
{"skip":3},
{"data": "/////w=="},
{"skip":38},
{"data": "////"},
{"skip":12},
{"data": "////"},
{"skip":6},
{"data": "//////8="},
{"skip":18},
{"data": "////"},
{"skip":5},
{"data": "////"},
{"skip":22},
{"data": "/////w=="},
{"skip":25},
{"data": "/////w=="},
{"skip":39},
{"data": "/////w=="},
{"skip":20},
{"data": "////"},
{"skip":3},
{"data": "////"},
{"skip":22},
{"data": "////"},
{"skip":4},
{"data": "////"},
{"skip":22},
{"data": "/////w=="},
{"skip":3},
{"data": "//8="},
{"skip":53},
{"data": "////"},
{"skip":8},
{"data": "////"},
{"skip":21},
{"data": "////"},
{"skip":3},
{"data": "////"},
{"skip":23},
{"data": "////"},
{"skip":3},
{"data": "////"},
{"skip":23},
{"data": "////"},
{"skip":4},
{"data": "////"},
{"skip":26},
{"data": "/////w=="},
{"skip":23},
{"data": "////"},
{"skip":19}],
    "cellWidth": 32,
    "cellHeight": 32
}